Workbook

Sheet STOCK
A1: Nombre | B1: TIPO | C1: Modelo | D1: Numero | E1: Piso | F1: Edificio | G1: m2Construido | H1: m2Balcon | I1: Orientacion | J1: Derecho | K1: EstadoInmueble | L1: Inmueble_Pack | M1: Obs | N1: Precio Lista | O1: Precio + Dcto | P1: Precio VENTA
A2: Alto Buzeta (MT) | B2: DEPARTAMENTO | C2: 1D1B | D2: 1520 | E2: 15 | F2: A | G2: 31.35 | H2: 2.85 | I2: Surponiente | J2: DOMINIO | K2: En Recolocación | N2: 2571 | O2: =IF(B2="DEPARTAMENTO",IF(C2="3D1B",N2*(100%-13%),N2*(100%-VLOOKUP(A2,'Condiciones Comerciales'!B:M,4,FALSE))),N2) -> 2313.9 | P2: =(O2-10%*O2)/80% -> 2603.1375
A3: Alto Buzeta (MT) | B3: DEPARTAMENTO | C3: 1D1BS | D3: 206 | E3: 2 | F3: A | G3: 24.02 | H3: 0 | I3: Norponiente | J3: DOMINIO | K3: Disponible | N3: 2029 | O3: =IF(B3="DEPARTAMENTO",IF(C3="3D1B",N3*(100%-13%),N3*(100%-VLOOKUP(A3,'Condiciones Comerciales'!B:M,4,FALSE))),N3) -> 1826.1 | P3: =(O3-10%*O3)/80% -> 2054.3625
A4: Alto Buzeta (MT) | B4: DEPARTAMENTO | C4: 1D1BS | D4: 1906 | E4: 19 | F4: A | G4: 23.93 | H4: 0 | I4: Norponiente | J4: DOMINIO | K4: Disponible | N4: 2181 | O4: =IF(B4="DEPARTAMENTO",IF(C4="3D1B",N4*(100%-13%),N4*(100%-VLOOKUP(A4,'Condiciones Comerciales'!B:M,4,FALSE))),N4) -> 1962.9 | P4: =(O4-10%*O4)/80% -> 2208.2625
A5: Alto Buzeta (MT) | B5: DEPARTAMENTO | C5: 1D1BSg | D5: 217 | E5: 2 | F5: A | G5: 29.76 | H5: 0 | I5: Surponiente | J5: DOMINIO | K5: Disponible | N5: 2444 | O5: =IF(B5="DEPARTAMENTO",IF(C5="3D1B",N5*(100%-13%),N5*(100%-VLOOKUP(A5,'Condiciones Comerciales'!B:M,4,FALSE))),N5) -> 2199.6 | P5: =(O5-10%*O5)/80% -> 2474.55
A6: Alto Buzeta (MT) | B6: DEPARTAMENTO | C6: 1D1BSg | D6: 317 | E6: 3 | F6: A | G6: 29.76 | H6: 0 | I6: Surponiente | J6: DOMINIO | K6: Disponible | N6: 2456 | O6: =IF(B6="DEPARTAMENTO",IF(C6="3D1B",N6*(100%-13%),N6*(100%-VLOOKUP(A6,'Condiciones Comerciales'!B:M,4,FALSE))),N6) -> 2210.4 | P6: =(O6-10%*O6)/80% -> 2486.7
A7: Alto Buzeta (MT) | B7: DEPARTAMENTO | C7: 1D1BSg | D7: 417 | E7: 4 | F7: A | G7: 29.76 | H7: 0 | I7: Surponiente | J7: DOMINIO | K7: Disponible | N7: 2468 | O7: =IF(B7="DEPARTAMENTO",IF(C7="3D1B",N7*(100%-13%),N7*(100%-VLOOKUP(A7,'Condiciones Comerciales'!B:M,4,FALSE))),N7) -> 2221.2 | P7: =(O7-10%*O7)/80% -> 2498.85
A8: Alto Buzeta (MT) | B8: DEPARTAMENTO | C8: 2D1B | D8: 619 | E8: 6 | F8: A | G8: 37.18 | H8: 2.25 | I8: Surponiente | J8: DOMINIO | K8: Disponible | N8: 2709 | O8: =IF(B8="DEPARTAMENTO",IF(C8="3D1B",N8*(100%-13%),N8*(100%-VLOOKUP(A8,'Condiciones Comerciales'!B:M,4,FALSE))),N8) -> 2438.1 | P8: =(O8-10%*O8)/80% -> 2742.8625
A9: Alto Buzeta (MT) | B9: DEPARTAMENTO | C9: 2D1B | D9: 807 | E9: 8 | F9: A | G9: 36.14 | H9: 2.05 | I9: Norponiente | J9: DOMINIO | K9: En Recolocación | N9: 2770 | O9: =IF(B9="DEPARTAMENTO",IF(C9="3D1B",N9*(100%-13%),N9*(100%-VLOOKUP(A9,'Condiciones Comerciales'!B:M,4,FALSE))),N9) -> 2493 | P9: =(O9-10%*O9)/80% -> 2804.625
A10: Alto Buzeta (MT) | B10: DEPARTAMENTO | C10: 2D1B | D10: 907 | E10: 9 | F10: A | G10: 36.14 | H10: 2.05 | I10: Norponiente | J10: DOMINIO | K10: Disponible | N10: 2782 | O10: =IF(B10="DEPARTAMENTO",IF(C10="3D1B",N10*(100%-13%),N10*(100%-VLOOKUP(A10,'Condiciones Comerciales'!B:M,4,FALSE))),N10) -> 2503.8 | P10: =(O10-10%*O10)/80% -> 2816.775
A11: Alto Buzeta (MT) | B11: DEPARTAMENTO | C11: 2Dg1B | D11: 103 | E11: 1 | F11: A | G11: 45.61 | H11: 2.66 | I11: Suroriente | J11: DOMINIO | K11: Disponible | L11: B - 64 | N11: 2932 | O11: =IF(B11="DEPARTAMENTO",IF(C11="3D1B",N11*(100%-13%),N11*(100%-VLOOKUP(A11,'Condiciones Comerciales'!B:M,4,FALSE))),N11) -> 2638.8 | P11: =(O11-10%*O11)/80% -> 2968.65
A12: Alto Buzeta (MT) | B12: DEPARTAMENTO | C12: 2Dg1B | D12: 304 | E12: 3 | F12: A | G12: 46.07 | H12: 2.75 | I12: Norponiente | J12: DOMINIO | K12: En Recolocación | N12: 3029 | O12: =IF(B12="DEPARTAMENTO",IF(C12="3D1B",N12*(100%-13%),N12*(100%-VLOOKUP(A12,'Condiciones Comerciales'!B:M,4,FALSE))),N12) -> 2726.1 | P12: =(O12-10%*O12)/80% -> 3066.8625
A13: Alto Buzeta (MT) | B13: DEPARTAMENTO | C13: 2Dg1B | D13: 309 | E13: 3 | F13: A | G13: 43.49 | H13: 2.24 | I13: Norponiente | J13: DOMINIO | K13: En Recolocación | N13: 3029 | O13: =IF(B13="DEPARTAMENTO",IF(C13="3D1B",N13*(100%-13%),N13*(100%-VLOOKUP(A13,'Condiciones Comerciales'!B:M,4,FALSE))),N13) -> 2726.1 | P13: =(O13-10%*O13)/80% -> 3066.8625
A14: Alto Buzeta (MT) | B14: DEPARTAMENTO | C14: 2Dg1B | D14: 313 | E14: 3 | F14: A | G14: 45.93 | H14: 2.77 | I14: Nororiente | J14: DOMINIO | K14: En Recolocación | N14: 3053 | O14: =IF(B14="DEPARTAMENTO",IF(C14="3D1B",N14*(100%-13%),N14*(100%-VLOOKUP(A14,'Condiciones Comerciales'!B:M,4,FALSE))),N14) -> 2747.7 | P14: =(O14-10%*O14)/80% -> 3091.1625
A15: Alto Buzeta (MT) | B15: DEPARTAMENTO | C15: 2Dg1B | D15: 415 | E15: 4 | F15: A | G15: 43.34 | H15: 2.24 | I15: Nororiente | J15: DOMINIO | K15: En Recolocación | N15: 3065 | O15: =IF(B15="DEPARTAMENTO",IF(C15="3D1B",N15*(100%-13%),N15*(100%-VLOOKUP(A15,'Condiciones Comerciales'!B:M,4,FALSE))),N15) -> 2758.5 | P15: =(O15-10%*O15)/80% -> 3103.3125
A16: Alto Buzeta (MT) | B16: DEPARTAMENTO | C16: 2Dg1B | D16: 505 | E16: 5 | F16: A | G16: 43.61 | H16: 2.24 | I16: Norponiente | J16: DOMINIO | K16: En Recolocación | N16: 3053 | O16: =IF(B16="DEPARTAMENTO",IF(C16="3D1B",N16*(100%-13%),N16*(100%-VLOOKUP(A16,'Condiciones Comerciales'!B:M,4,FALSE))),N16) -> 2747.7 | P16: =(O16-10%*O16)/80% -> 3091.1625
A17: Alto Buzeta (MT) | B17: DEPARTAMENTO | C17: 2Dg1B | D17: 508 | E17: 5 | F17: A | G17: 43.1 | H17: 2.24 | I17: Norponiente | J17: DOMINIO | K17: En Recolocación | N17: 3053 | O17: =IF(B17="DEPARTAMENTO",IF(C17="3D1B",N17*(100%-13%),N17*(100%-VLOOKUP(A17,'Condiciones Comerciales'!B:M,4,FALSE))),N17) -> 2747.7 | P17: =(O17-10%*O17)/80% -> 3091.1625
A18: Alto Buzeta (MT) | B18: DEPARTAMENTO | C18: 2Dg1B | D18: 605 | E18: 6 | F18: A | G18: 43.61 | H18: 2.24 | I18: Norponiente | J18: DOMINIO | K18: En Recolocación | N18: 3065 | O18: =IF(B18="DEPARTAMENTO",IF(C18="3D1B",N18*(100%-13%),N18*(100%-VLOOKUP(A18,'Condiciones Comerciales'!B:M,4,FALSE))),N18) -> 2758.5 | P18: =(O18-10%*O18)/80% -> 3103.3125
A19: Alto Buzeta (MT) | B19: DEPARTAMENTO | C19: 2Dg1B | D19: 608 | E19: 6 | F19: A | G19: 43.1 | H19: 2.24 | I19: Norponiente | J19: DOMINIO | K19: En Recolocación | N19: 3065 | O19: =IF(B19="DEPARTAMENTO",IF(C19="3D1B",N19*(100%-13%),N19*(100%-VLOOKUP(A19,'Condiciones Comerciales'!B:M,4,FALSE))),N19) -> 2758.5 | P19: =(O19-10%*O19)/80% -> 3103.3125
A20: Alto Buzeta (MT) | B20: DEPARTAMENTO | C20: 2Dg1B | D20: 609 | E20: 6 | F20: A | G20: 43.49 | H20: 2.24 | I20: Norponiente | J20: DOMINIO | K20: Disponible | N20: 3065 | O20: =IF(B20="DEPARTAMENTO",IF(C20="3D1B",N20*(100%-13%),N20*(100%-VLOOKUP(A20,'Condiciones Comerciales'!B:M,4,FALSE))),N20) -> 2758.5 | P20: =(O20-10%*O20)/80% -> 3103.3125
A21: Alto Buzeta (MT) | B21: DEPARTAMENTO | C21: 2Dg1B | D21: 613 | E21: 6 | F21: A | G21: 46.44 | H21: 2.77 | I21: Nororiente | J21: DOMINIO | K21: Disponible | N21: 3090 | O21: =IF(B21="DEPARTAMENTO",IF(C21="3D1B",N21*(100%-13%),N21*(100%-VLOOKUP(A21,'Condiciones Comerciales'!B:M,4,FALSE))),N21) -> 2781 | P21: =(O21-10%*O21)/80% -> 3128.625
A22: Alto Buzeta (MT) | B22: DEPARTAMENTO | C22: 2Dg1B | D22: 705 | E22: 7 | F22: A | G22: 43.61 | H22: 2.24 | I22: Norponiente | J22: DOMINIO | K22: Disponible | L22: B - 69 | N22: 3078 | O22: =IF(B22="DEPARTAMENTO",IF(C22="3D1B",N22*(100%-13%),N22*(100%-VLOOKUP(A22,'Condiciones Comerciales'!B:M,4,FALSE))),N22) -> 2770.2 | P22: =(O22-10%*O22)/80% -> 3116.475
A23: Alto Buzeta (MT) | B23: DEPARTAMENTO | C23: 2Dg1B | D23: 709 | E23: 7 | F23: A | G23: 43.49 | H23: 2.24 | I23: Norponiente | J23: DOMINIO | K23: Disponible | N23: 3078 | O23: =IF(B23="DEPARTAMENTO",IF(C23="3D1B",N23*(100%-13%),N23*(100%-VLOOKUP(A23,'Condiciones Comerciales'!B:M,4,FALSE))),N23) -> 2770.2 | P23: =(O23-10%*O23)/80% -> 3116.475
A24: Alto Buzeta (MT) | B24: DEPARTAMENTO | C24: 2Dg1B | D24: 713 | E24: 7 | F24: A | G24: 46.44 | H24: 2.77 | I24: Nororiente | J24: DOMINIO | K24: Disponible | N24: 3102 | O24: =IF(B24="DEPARTAMENTO",IF(C24="3D1B",N24*(100%-13%),N24*(100%-VLOOKUP(A24,'Condiciones Comerciales'!B:M,4,FALSE))),N24) -> 2791.8 | P24: =(O24-10%*O24)/80% -> 3140.775
A25: Alto Buzeta (MT) | B25: DEPARTAMENTO | C25: 2Dg1B | D25: 805 | E25: 8 | F25: A | G25: 43.61 | H25: 2.24 | I25: Norponiente | J25: DOMINIO | K25: Disponible | N25: 3090 | O25: =IF(B25="DEPARTAMENTO",IF(C25="3D1B",N25*(100%-13%),N25*(100%-VLOOKUP(A25,'Condiciones Comerciales'!B:M,4,FALSE))),N25) -> 2781 | P25: =(O25-10%*O25)/80% -> 3128.625
A26: Alto Buzeta (MT) | B26: DEPARTAMENTO | C26: 2Dg1B | D26: 808 | E26: 8 | F26: A | G26: 43.1 | H26: 2.24 | I26: Norponiente | J26: DOMINIO | K26: Disponible | N26: 3090 | O26: =IF(B26="DEPARTAMENTO",IF(C26="3D1B",N26*(100%-13%),N26*(100%-VLOOKUP(A26,'Condiciones Comerciales'!B:M,4,FALSE))),N26) -> 2781 | P26: =(O26-10%*O26)/80% -> 3128.625
A27: Alto Buzeta (MT) | B27: DEPARTAMENTO | C27: 2Dg1B | D27: 809 | E27: 8 | F27: A | G27: 43.49 | H27: 2.24 | I27: Norponiente | J27: DOMINIO | K27: Disponible | N27: 3090 | O27: =IF(B27="DEPARTAMENTO",IF(C27="3D1B",N27*(100%-13%),N27*(100%-VLOOKUP(A27,'Condiciones Comerciales'!B:M,4,FALSE))),N27) -> 2781 | P27: =(O27-10%*O27)/80% -> 3128.625
A28: Alto Buzeta (MT) | B28: DEPARTAMENTO | C28: 2Dg1B | D28: 813 | E28: 8 | F28: A | G28: 46.44 | H28: 2.77 | I28: Nororiente | J28: DOMINIO | K28: Disponible | N28: 3114 | O28: =IF(B28="DEPARTAMENTO",IF(C28="3D1B",N28*(100%-13%),N28*(100%-VLOOKUP(A28,'Condiciones Comerciales'!B:M,4,FALSE))),N28) -> 2802.6 | P28: =(O28-10%*O28)/80% -> 3152.925
A29: Alto Buzeta (MT) | B29: DEPARTAMENTO | C29: 2Dg1B | D29: 905 | E29: 9 | F29: A | G29: 43.61 | H29: 2.24 | I29: Norponiente | J29: DOMINIO | K29: Disponible | L29: B - 71 | N29: 3102 | O29: =IF(B29="DEPARTAMENTO",IF(C29="3D1B",N29*(100%-13%),N29*(100%-VLOOKUP(A29,'Condiciones Comerciales'!B:M,4,FALSE))),N29) -> 2791.8 | P29: =(O29-10%*O29)/80% -> 3140.775
A30: Alto Buzeta (MT) | B30: DEPARTAMENTO | C30: 2Dg1B | D30: 908 | E30: 9 | F30: A | G30: 43.1 | H30: 2.24 | I30: Norponiente | J30: DOMINIO | K30: Disponible | N30: 3102 | O30: =IF(B30="DEPARTAMENTO",IF(C30="3D1B",N30*(100%-13%),N30*(100%-VLOOKUP(A30,'Condiciones Comerciales'!B:M,4,FALSE))),N30) -> 2791.8 | P30: =(O30-10%*O30)/80% -> 3140.775
A31: Alto Buzeta (MT) | B31: DEPARTAMENTO | C31: 2Dg1B | D31: 909 | E31: 9 | F31: A | G31: 43.49 | H31: 2.24 | I31: Norponiente | J31: DOMINIO | K31: Disponible | N31: 3102 | O31: =IF(B31="DEPARTAMENTO",IF(C31="3D1B",N31*(100%-13%),N31*(100%-VLOOKUP(A31,'Condiciones Comerciales'!B:M,4,FALSE))),N31) -> 2791.8 | P31: =(O31-10%*O31)/80% -> 3140.775
A32: Alto Buzeta (MT) | B32: DEPARTAMENTO | C32: 2Dg1B | D32: 913 | E32: 9 | F32: A | G32: 46.44 | H32: 2.77 | I32: Nororiente | J32: DOMINIO | K32: Disponible | N32: 3126 | O32: =IF(B32="DEPARTAMENTO",IF(C32="3D1B",N32*(100%-13%),N32*(100%-VLOOKUP(A32,'Condiciones Comerciales'!B:M,4,FALSE))),N32) -> 2813.4 | P32: =(O32-10%*O32)/80% -> 3165.075
A33: Alto Buzeta (MT) | B33: DEPARTAMENTO | C33: 2Dg1B | D33: 918 | E33: 9 | F33: A | G33: 46.44 | H33: 2.77 | I33: Surponiente | J33: DOMINIO | K33: Disponible | N33: 3065 | O33: =IF(B33="DEPARTAMENTO",IF(C33="3D1B",N33*(100%-13%),N33*(100%-VLOOKUP(A33,'Condiciones Comerciales'!B:M,4,FALSE))),N33) -> 2758.5 | P33: =(O33-10%*O33)/80% -> 3103.3125
A34: Alto Buzeta (MT) | B34: DEPARTAMENTO | C34: 2Dg1B | D34: 1005 | E34: 10 | F34: A | G34: 43.61 | H34: 2.24 | I34: Norponiente | J34: DOMINIO | K34: Disponible | N34: 3114 | O34: =IF(B34="DEPARTAMENTO",IF(C34="3D1B",N34*(100%-13%),N34*(100%-VLOOKUP(A34,'Condiciones Comerciales'!B:M,4,FALSE))),N34) -> 2802.6 | P34: =(O34-10%*O34)/80% -> 3152.925
A35: Alto Buzeta (MT) | B35: DEPARTAMENTO | C35: 2Dg1B | D35: 1008 | E35: 10 | F35: A | G35: 43.1 | H35: 2.24 | I35: Norponiente | J35: DOMINIO | K35: Disponible | N35: 3114 | O35: =IF(B35="DEPARTAMENTO",IF(C35="3D1B",N35*(100%-13%),N35*(100%-VLOOKUP(A35,'Condiciones Comerciales'!B:M,4,FALSE))),N35) -> 2802.6 | P35: =(O35-10%*O35)/80% -> 3152.925
A36: Alto Buzeta (MT) | B36: DEPARTAMENTO | C36: 2Dg1B | D36: 1009 | E36: 10 | F36: A | G36: 43.49 | H36: 2.24 | I36: Norponiente | J36: DOMINIO | K36: Disponible | N36: 3114 | O36: =IF(B36="DEPARTAMENTO",IF(C36="3D1B",N36*(100%-13%),N36*(100%-VLOOKUP(A36,'Condiciones Comerciales'!B:M,4,FALSE))),N36) -> 2802.6 | P36: =(O36-10%*O36)/80% -> 3152.925
A37: Alto Buzeta (MT) | B37: DEPARTAMENTO | C37: 2Dg1B | D37: 1013 | E37: 10 | F37: A | G37: 46.44 | H37: 2.77 | I37: Nororiente | J37: DOMINIO | K37: Disponible | N37: 3138 | O37: =IF(B37="DEPARTAMENTO",IF(C37="3D1B",N37*(100%-13%),N37*(100%-VLOOKUP(A37,'Condiciones Comerciales'!B:M,4,FALSE))),N37) -> 2824.2 | P37: =(O37-10%*O37)/80% -> 3177.225
A38: Alto Buzeta (MT) | B38: DEPARTAMENTO | C38: 2Dg1B | D38: 1018 | E38: 10 | F38: A | G38: 46.44 | H38: 2.77 | I38: Surponiente | J38: DOMINIO | K38: Disponible | N38: 3078 | O38: =IF(B38="DEPARTAMENTO",IF(C38="3D1B",N38*(100%-13%),N38*(100%-VLOOKUP(A38,'Condiciones Comerciales'!B:M,4,FALSE))),N38) -> 2770.2 | P38: =(O38-10%*O38)/80% -> 3116.475
A39: Alto Buzeta (MT) | B39: DEPARTAMENTO | C39: 2Dg1B | D39: 1108 | E39: 11 | F39: A | G39: 43.1 | H39: 2.24 | I39: Norponiente | J39: DOMINIO | K39: Disponible | N39: 3120 | O39: =IF(B39="DEPARTAMENTO",IF(C39="3D1B",N39*(100%-13%),N39*(100%-VLOOKUP(A39,'Condiciones Comerciales'!B:M,4,FALSE))),N39) -> 2808 | P39: =(O39-10%*O39)/80% -> 3159
A40: Alto Buzeta (MT) | B40: DEPARTAMENTO | C40: 2Dg1B | D40: 1109 | E40: 11 | F40: A | G40: 43.49 | H40: 2.24 | I40: Norponiente | J40: DOMINIO | K40: Disponible | N40: 3120 | O40: =IF(B40="DEPARTAMENTO",IF(C40="3D1B",N40*(100%-13%),N40*(100%-VLOOKUP(A40,'Condiciones Comerciales'!B:M,4,FALSE))),N40) -> 2808 | P40: =(O40-10%*O40)/80% -> 3159
A41: Alto Buzeta (MT) | B41: DEPARTAMENTO | C41: 2Dg1B | D41: 1113 | E41: 11 | F41: A | G41: 46.44 | H41: 2.77 | I41: Nororiente | J41: DOMINIO | K41: Disponible | N41: 3144 | O41: =IF(B41="DEPARTAMENTO",IF(C41="3D1B",N41*(100%-13%),N41*(100%-VLOOKUP(A41,'Condiciones Comerciales'!B:M,4,FALSE))),N41) -> 2829.6 | P41: =(O41-10%*O41)/80% -> 3183.3
... A47: Alto Buzeta (MT) | B47: DEPARTAMENTO | C47: 2Dg1B | D47: 1218 | E47: 12 | F47: A | G47: 46.44 | H47: 2.77 | I47: Surponiente | J47: DOMINIO | K47: Disponible | N47: 3090 | O47: =IF(B47="DEPARTAMENTO",IF(C47="3D1B",N47*(100%-13%),N47*(100%-VLOOKUP(A47,'Condiciones Comerciales'!B:M,4,FALSE))),N47) -> 2781 | P47: =(O47-10%*O47)/80% -> 3128.625
A48: Alto Buzeta (MT) | B48: DEPARTAMENTO | C48: 2Dg1B | D48: 1305 | E48: 13 | F48: A | G48: 43.61 | H48: 2.24 | I48: Norponiente | J48: DOMINIO | K48: Disponible | L48: B - 75 | N48: 3132 | O48: =IF(B48="DEPARTAMENTO",IF(C48="3D1B",N48*(100%-13%),N48*(100%-VLOOKUP(A48,'Condiciones Comerciales'!B:M,4,FALSE))),N48) -> 2818.8 | P48: =(O48-10%*O48)/80% -> 3171.15
A49: Alto Buzeta (MT) | B49: DEPARTAMENTO | C49: 2Dg1B | D49: 1308 | E49: 13 | F49: A | G49: 43.1 | H49: 2.24 | I49: Norponiente | J49: DOMINIO | K49: Disponible | N49: 3132 | O49: =IF(B49="DEPARTAMENTO",IF(C49="3D1B",N49*(100%-13%),N49*(100%-VLOOKUP(A49,'Condiciones Comerciales'!B:M,4,FALSE))),N49) -> 2818.8 | P49: =(O49-10%*O49)/80% -> 3171.15
A50: Alto Buzeta (MT) | B50: DEPARTAMENTO | C50: 2Dg1B | D50: 1309 | E50: 13 | F50: A | G50: 43.49 | H50: 2.24 | I50: Norponiente | J50: DOMINIO | K50: Disponible | N50: 3132 | O50: =IF(B50="DEPARTAMENTO",IF(C50="3D1B",N50*(100%-13%),N50*(100%-VLOOKUP(A50,'Condiciones Comerciales'!B:M,4,FALSE))),N50) -> 2818.8 | P50: =(O50-10%*O50)/80% -> 3171.15
A51: Alto Buzeta (MT) | B51: DEPARTAMENTO | C51: 2Dg1B | D51: 1313 | E51: 13 | F51: A | G51: 46.44 | H51: 2.77 | I51: Nororiente | J51: DOMINIO | K51: Disponible | N51: 3156 | O51: =IF(B51="DEPARTAMENTO",IF(C51="3D1B",N51*(100%-13%),N51*(100%-VLOOKUP(A51,'Condiciones Comerciales'!B:M,4,FALSE))),N51) -> 2840.4 | P51: =(O51-10%*O51)/80% -> 3195.45
A52: Alto Buzeta (MT) | B52: DEPARTAMENTO | C52: 2Dg1B | D52: 1318 | E52: 13 | F52: A | G52: 46.44 | H52: 2.77 | I52: Surponiente | J52: DOMINIO | K52: Disponible | N52: 3096 | O52: =IF(B52="DEPARTAMENTO",IF(C52="3D1B",N52*(100%-13%),N52*(100%-VLOOKUP(A52,'Condiciones Comerciales'!B:M,4,FALSE))),N52) -> 2786.4 | P52: =(O52-10%*O52)/80% -> 3134.7
A53: Alto Buzeta (MT) | B53: DEPARTAMENTO | C53: 2Dg1B | D53: 1405 | E53: 14 | F53: A | G53: 43.61 | H53: 2.24 | I53: Norponiente | J53: DOMINIO | K53: Disponible | N53: 3138 | O53: =IF(B53="DEPARTAMENTO",IF(C53="3D1B",N53*(100%-13%),N53*(100%-VLOOKUP(A53,'Condiciones Comerciales'!B:M,4,FALSE))),N53) -> 2824.2 | P53: =(O53-10%*O53)/80% -> 3177.225
A54: Alto Buzeta (MT) | B54: DEPARTAMENTO | C54: 2Dg1B | D54: 1408 | E54: 14 | F54: A | G54: 43.1 | H54: 2.24 | I54: Norponiente | J54: DOMINIO | K54: Disponible | N54: 3138 | O54: =IF(B54="DEPARTAMENTO",IF(C54="3D1B",N54*(100%-13%),N54*(100%-VLOOKUP(A54,'Condiciones Comerciales'!B:M,4,FALSE))),N54) -> 2824.2 | P54: =(O54-10%*O54)/80% -> 3177.225
A55: Alto Buzeta (MT) | B55: DEPARTAMENTO | C55: 2Dg1B | D55: 1409 | E55: 14 | F55: A | G55: 43.49 | H55: 2.24 | I55: Norponiente | J55: DOMINIO | K55: Disponible | N55: 3138 | O55: =IF(B55="DEPARTAMENTO",IF(C55="3D1B",N55*(100%-13%),N55*(100%-VLOOKUP(A55,'Condiciones Comerciales'!B:M,4,FALSE))),N55) -> 2824.2 | P55: =(O55-10%*O55)/80% -> 3177.225
A56: Alto Buzeta (MT) | B56: DEPARTAMENTO | C56: 2Dg1B | D56: 1413 | E56: 14 | F56: A | G56: 46.44 | H56: 2.77 | I56: Nororiente | J56: DOMINIO | K56: Disponible | N56: 3162 | O56: =IF(B56="DEPARTAMENTO",IF(C56="3D1B",N56*(100%-13%),N56*(100%-VLOOKUP(A56,'Condiciones Comerciales'!B:M,4,FALSE))),N56) -> 2845.8 | P56: =(O56-10%*O56)/80% -> 3201.525
A57: Alto Buzeta (MT) | B57: DEPARTAMENTO | C57: 2Dg1B | D57: 1418 | E57: 14 | F57: A | G57: 46.44 | H57: 2.77 | I57: Surponiente | J57: DOMINIO | K57: Disponible | N57: 3102 | O57: =IF(B57="DEPARTAMENTO",IF(C57="3D1B",N57*(100%-13%),N57*(100%-VLOOKUP(A57,'Condiciones Comerciales'!B:M,4,FALSE))),N57) -> 2791.8 | P57: =(O57-10%*O57)/80% -> 3140.775
A58: Alto Buzeta (MT) | B58: DEPARTAMENTO | C58: 2Dg1B | D58: 1505 | E58: 15 | F58: A | G58: 43.61 | H58: 2.24 | I58: Norponiente | J58: DOMINIO | K58: Disponible | L58: B - 77 | N58: 3144 | O58: =IF(B58="DEPARTAMENTO",IF(C58="3D1B",N58*(100%-13%),N58*(100%-VLOOKUP(A58,'Condiciones Comerciales'!B:M,4,FALSE))),N58) -> 2829.6 | P58: =(O58-10%*O58)/80% -> 3183.3
A59: Alto Buzeta (MT) | B59: DEPARTAMENTO | C59: 2Dg1B | D59: 1508 | E59: 15 | F59: A | G59: 43.1 | H59: 2.24 | I59: Norponiente | J59: DOMINIO | K59: Disponible | N59: 3144 | O59: =IF(B59="DEPARTAMENTO",IF(C59="3D1B",N59*(100%-13%),N59*(100%-VLOOKUP(A59,'Condiciones Comerciales'!B:M,4,FALSE))),N59) -> 2829.6 | P59: =(O59-10%*O59)/80% -> 3183.3
A60: Alto Buzeta (MT) | B60: DEPARTAMENTO | C60: 2Dg1B | D60: 1509 | E60: 15 | F60: A | G60: 43.49 | H60: 2.24 | I60: Norponiente | J60: DOMINIO | K60: Disponible | N60: 3144 | O60: =IF(B60="DEPARTAMENTO",IF(C60="3D1B",N60*(100%-13%),N60*(100%-VLOOKUP(A60,'Condiciones Comerciales'!B:M,4,FALSE))),N60) -> 2829.6 | P60: =(O60-10%*O60)/80% -> 3183.3
A61: Alto Buzeta (MT) | B61: DEPARTAMENTO | C61: 2Dg1B | D61: 1513 | E61: 15 | F61: A | G61: 46.44 | H61: 2.77 | I61: Nororiente | J61: DOMINIO | K61: Disponible | N61: 3168 | O61: =IF(B61="DEPARTAMENTO",IF(C61="3D1B",N61*(100%-13%),N61*(100%-VLOOKUP(A61,'Condiciones Comerciales'!B:M,4,FALSE))),N61) -> 2851.2 | P61: =(O61-10%*O61)/80% -> 3207.6
A62: Alto Buzeta (MT) | B62: DEPARTAMENTO | C62: 2Dg1B | D62: 1518 | E62: 15 | F62: A | G62: 46.44 | H62: 2.77 | I62: Surponiente | J62: DOMINIO | K62: Disponible | N62: 3108 | O62: =IF(B62="DEPARTAMENTO",IF(C62="3D1B",N62*(100%-13%),N62*(100%-VLOOKUP(A62,'Condiciones Comerciales'!B:M,4,FALSE))),N62) -> 2797.2 | P62: =(O62-10%*O62)/80% -> 3146.85
A63: Alto Buzeta (MT) | B63: DEPARTAMENTO | C63: 2Dg1B | D63: 1605 | E63: 16 | F63: A | G63: 43.61 | H63: 2.24 | I63: Norponiente | J63: DOMINIO | K63: Disponible | N63: 3150 | O63: =IF(B63="DEPARTAMENTO",IF(C63="3D1B",N63*(100%-13%),N63*(100%-VLOOKUP(A63,'Condiciones Comerciales'!B:M,4,FALSE))),N63) -> 2835 | P63: =(O63-10%*O63)/80% -> 3189.375
A64: Alto Buzeta (MT) | B64: DEPARTAMENTO | C64: 2Dg1B | D64: 1608 | E64: 16 | F64: A | G64: 43.1 | H64: 2.24 | I64: Norponiente | J64: DOMINIO | K64: Disponible | N64: 3150 | O64: =IF(B64="DEPARTAMENTO",IF(C64="3D1B",N64*(100%-13%),N64*(100%-VLOOKUP(A64,'Condiciones Comerciales'!B:M,4,FALSE))),N64) -> 2835 | P64: =(O64-10%*O64)/80% -> 3189.375
A65: Alto Buzeta (MT) | B65: DEPARTAMENTO | C65: 2Dg1B | D65: 1609 | E65: 16 | F65: A | G65: 43.49 | H65: 2.24 | I65: Norponiente | J65: DOMINIO | K65: Disponible | N65: 3150 | O65: =IF(B65="DEPARTAMENTO",IF(C65="3D1B",N65*(100%-13%),N65*(100%-VLOOKUP(A65,'Condiciones Comerciales'!B:M,4,FALSE))),N65) -> 2835 | P65: =(O65-10%*O65)/80% -> 3189.375
A66: Alto Buzeta (MT) | B66: DEPARTAMENTO | C66: 2Dg1B | D66: 1613 | E66: 16 | F66: A | G66: 46.44 | H66: 2.77 | I66: Nororiente | J66: DOMINIO | K66: Disponible | N66: 3175 | O66: =IF(B66="DEPARTAMENTO",IF(C66="3D1B",N66*(100%-13%),N66*(100%-VLOOKUP(A66,'Condiciones Comerciales'!B:M,4,FALSE))),N66) -> 2857.5 | P66: =(O66-10%*O66)/80% -> 3214.6875
A67: Alto Buzeta (MT) | B67: DEPARTAMENTO | C67: 2Dg1B | D67: 1618 | E67: 16 | F67: A | G67: 46.44 | H67: 2.77 | I67: Surponiente | J67: DOMINIO | K67: Disponible | N67: 3114 | O67: =IF(B67="DEPARTAMENTO",IF(C67="3D1B",N67*(100%-13%),N67*(100%-VLOOKUP(A67,'Condiciones Comerciales'!B:M,4,FALSE))),N67) -> 2802.6 | P67: =(O67-10%*O67)/80% -> 3152.925
A68: Alto Buzeta (MT) | B68: DEPARTAMENTO | C68: 2Dg1B | D68: 1705 | E68: 17 | F68: A | G68: 43.61 | H68: 2.24 | I68: Norponiente | J68: DOMINIO | K68: Disponible | L68: B - 79 | N68: 3156 | O68: =IF(B68="DEPARTAMENTO",IF(C68="3D1B",N68*(100%-13%),N68*(100%-VLOOKUP(A68,'Condiciones Comerciales'!B:M,4,FALSE))),N68) -> 2840.4 | P68: =(O68-10%*O68)/80% -> 3195.45
A69: Alto Buzeta (MT) | B69: DEPARTAMENTO | C69: 2Dg1B | D69: 1708 | E69: 17 | F69: A | G69: 43.1 | H69: 2.24 | I69: Norponiente | J69: DOMINIO | K69: Disponible | N69: 3156 | O69: =IF(B69="DEPARTAMENTO",IF(C69="3D1B",N69*(100%-13%),N69*(100%-VLOOKUP(A69,'Condiciones Comerciales'!B:M,4,FALSE))),N69) -> 2840.4 | P69: =(O69-10%*O69)/80% -> 3195.45
A70: Alto Buzeta (MT) | B70: DEPARTAMENTO | C70: 2Dg1B | D70: 1709 | E70: 17 | F70: A | G70: 43.49 | H70: 2.24 | I70: Norponiente | J70: DOMINIO | K70: Disponible | N70: 3156 | O70: =IF(B70="DEPARTAMENTO",IF(C70="3D1B",N70*(100%-13%),N70*(100%-VLOOKUP(A70,'Condiciones Comerciales'!B:M,4,FALSE))),N70) -> 2840.4 | P70: =(O70-10%*O70)/80% -> 3195.45
A71: Alto Buzeta (MT) | B71: DEPARTAMENTO | C71: 2Dg1B | D71: 1713 | E71: 17 | F71: A | G71: 46.44 | H71: 2.77 | I71: Nororiente | J71: DOMINIO | K71: Disponible | N71: 3181 | O71: =IF(B71="DEPARTAMENTO",IF(C71="3D1B",N71*(100%-13%),N71*(100%-VLOOKUP(A71,'Condiciones Comerciales'!B:M,4,FALSE))),N71) -> 2862.9 | P71: =(O71-10%*O71)/80% -> 3220.7625
A72: Alto Buzeta (MT) | B72: DEPARTAMENTO | C72: 2Dg1B | D72: 1805 | E72: 18 | F72: A | G72: 43.61 | H72: 2.24 | I72: Norponiente | J72: DOMINIO | K72: Disponible | N72: 3162 | O72: =IF(B72="DEPARTAMENTO",IF(C72="3D1B",N72*(100%-13%),N72*(100%-VLOOKUP(A72,'Condiciones Comerciales'!B:M,4,FALSE))),N72) -> 2845.8 | P72: =(O72-10%*O72)/80% -> 3201.525
A73: Alto Buzeta (MT) | B73: DEPARTAMENTO | C73: 2Dg1B | D73: 1808 | E73: 18 | F73: A | G73: 43.1 | H73: 2.24 | I73: Norponiente | J73: DOMINIO | K73: Disponible | N73: 3162 | O73: =IF(B73="DEPARTAMENTO",IF(C73="3D1B",N73*(100%-13%),N73*(100%-VLOOKUP(A73,'Condiciones Comerciales'!B:M,4,FALSE))),N73) -> 2845.8 | P73: =(O73-10%*O73)/80% -> 3201.525
A74: Alto Buzeta (MT) | B74: DEPARTAMENTO | C74: 2Dg1B | D74: 1809 | E74: 18 | F74: A | G74: 43.49 | H74: 2.24 | I74: Norponiente | J74: DOMINIO | K74: Disponible | N74: 3162 | O74: =IF(B74="DEPARTAMENTO",IF(C74="3D1B",N74*(100%-13%),N74*(100%-VLOOKUP(A74,'Condiciones Comerciales'!B:M,4,FALSE))),N74) -> 2845.8 | P74: =(O74-10%*O74)/80% -> 3201.525
A75: Alto Buzeta (MT) | B75: DEPARTAMENTO | C75: 2Dg1B | D75: 1813 | E75: 18 | F75: A | G75: 46.44 | H75: 2.77 | I75: Nororiente | J75: DOMINIO | K75: Disponible | N75: 3187 | O75: =IF(B75="DEPARTAMENTO",IF(C75="3D1B",N75*(100%-13%),N75*(100%-VLOOKUP(A75,'Condiciones Comerciales'!B:M,4,FALSE))),N75) -> 2868.3 | P75: =(O75-10%*O75)/80% -> 3226.8375
A76: Alto Buzeta (MT) | B76: DEPARTAMENTO | C76: 2Dg1B | D76: 1905 | E76: 19 | F76: A | G76: 43.61 | H76: 2.24 | I76: Norponiente | J76: DOMINIO | K76: Disponible | L76: B - 81 | N76: 3168 | O76: =IF(B76="DEPARTAMENTO",IF(C76="3D1B",N76*(100%-13%),N76*(100%-VLOOKUP(A76,'Condiciones Comerciales'!B:M,4,FALSE))),N76) -> 2851.2 | P76: =(O76-10%*O76)/80% -> 3207.6
A77: Alto Buzeta (MT) | B77: DEPARTAMENTO | C77: 2Dg1B | D77: 1908 | E77: 19 | F77: A | G77: 43.1 | H77: 2.24 | I77: Norponiente | J77: DOMINIO | K77: Disponible | N77: 3168 | O77: =IF(B77="DEPARTAMENTO",IF(C77="3D1B",N77*(100%-13%),N77*(100%-VLOOKUP(A77,'Condiciones Comerciales'!B:M,4,FALSE))),N77) -> 2851.2 | P77: =(O77-10%*O77)/80% -> 3207.6
A78: Alto Buzeta (MT) | B78: DEPARTAMENTO | C78: 2Dg1B | D78: 1909 | E78: 19 | F78: A | G78: 43.49 | H78: 2.24 | I78: Norponiente | J78: DOMINIO | K78: Disponible | N78: 3168 | O78: =IF(B78="DEPARTAMENTO",IF(C78="3D1B",N78*(100%-13%),N78*(100%-VLOOKUP(A78,'Condiciones Comerciales'!B:M,4,FALSE))),N78) -> 2851.2 | P78: =(O78-10%*O78)/80% -> 3207.6
A79: Alto Buzeta (MT) | B79: DEPARTAMENTO | C79: 2Dg1B | D79: 2005 | E79: 20 | F79: A | G79: 43.61 | H79: 2.24 | I79: Norponiente | J79: DOMINIO | K79: Disponible | N79: 3175 | O79: =IF(B79="DEPARTAMENTO",IF(C79="3D1B",N79*(100%-13%),N79*(100%-VLOOKUP(A79,'Condiciones Comerciales'!B:M,4,FALSE))),N79) -> 2857.5 | P79: =(O79-10%*O79)/80% -> 3214.6875
A80: Alto Buzeta (MT) | B80: DEPARTAMENTO | C80: 2Dg1B | D80: 2008 | E80: 20 | F80: A | G80: 43.77 | H80: 2.24 | I80: Norponiente | J80: DOMINIO | K80: Disponible | N80: 3175 | O80: =IF(B80="DEPARTAMENTO",IF(C80="3D1B",N80*(100%-13%),N80*(100%-VLOOKUP(A80,'Condiciones Comerciales'!B:M,4,FALSE))),N80) -> 2857.5 | P80: =(O80-10%*O80)/80% -> 3214.6875
A81: Alto Buzeta (MT) | B81: DEPARTAMENTO | C81: 3D1B | D81: 301 | E81: 3 | F81: A | G81: 46.55 | H81: 2.26 | I81: Suroriente | J81: DOMINIO | K81: Disponible | N81: 3198 | O81: =IF(B81="DEPARTAMENTO",IF(C81="3D1B",N81*(100%-13%),N81*(100%-VLOOKUP(A81,'Condiciones Comerciales'!B:M,4,FALSE))),N81) -> 2782.26 | P81: =(O81-10%*O81)/80% -> 3130.0425
A82: Alto Buzeta (MT) | B82: DEPARTAMENTO | C82: 3D1B | D82: 702 | E82: 7 | F82: A | G82: 47.06 | H82: 2.26 | I82: Suroriente | J82: DOMINIO | K82: Disponible | N82: 3246 | O82: =IF(B82="DEPARTAMENTO",IF(C82="3D1B",N82*(100%-13%),N82*(100%-VLOOKUP(A82,'Condiciones Comerciales'!B:M,4,FALSE))),N82) -> 2824.02 | P82: =(O82-10%*O82)/80% -> 3177.0225
A83: Alto Buzeta (MT) | B83: DEPARTAMENTO | C83: 3D1B | D83: 801 | E83: 8 | F83: A | G83: 46.55 | H83: 2.26 | I83: Suroriente | J83: DOMINIO | K83: Disponible | N83: 3258 | O83: =IF(B83="DEPARTAMENTO",IF(C83="3D1B",N83*(100%-13%),N83*(100%-VLOOKUP(A83,'Condiciones Comerciales'!B:M,4,FALSE))),N83) -> 2834.46 | P83: =(O83-10%*O83)/80% -> 3188.7675
A84: Alto Buzeta (MT) | B84: DEPARTAMENTO | C84: 3D1B | D84: 802 | E84: 8 | F84: A | G84: 47.06 | H84: 2.26 | I84: Suroriente | J84: DOMINIO | K84: Disponible | L84: B - 70 | N84: 3258 | O84: =IF(B84="DEPARTAMENTO",IF(C84="3D1B",N84*(100%-13%),N84*(100%-VLOOKUP(A84,'Condiciones Comerciales'!B:M,4,FALSE))),N84) -> 2834.46 | P84: =(O84-10%*O84)/80% -> 3188.7675
A85: Alto Buzeta (MT) | B85: DEPARTAMENTO | C85: 3D1B | D85: 901 | E85: 9 | F85: A | G85: 46.55 | H85: 2.26 | I85: Suroriente | J85: DOMINIO | K85: Disponible | N85: 3270 | O85: =IF(B85="DEPARTAMENTO",IF(C85="3D1B",N85*(100%-13%),N85*(100%-VLOOKUP(A85,'Condiciones Comerciales'!B:M,4,FALSE))),N85) -> 2844.9 | P85: =(O85-10%*O85)/80% -> 3200.5125
A86: Alto Buzeta (MT) | B86: DEPARTAMENTO | C86: 3D1B | D86: 902 | E86: 9 | F86: A | G86: 47.06 | H86: 2.26 | I86: Suroriente | J86: DOMINIO | K86: Disponible | N86: 3270 | O86: =IF(B86="DEPARTAMENTO",IF(C86="3D1B",N86*(100%-13%),N86*(100%-VLOOKUP(A86,'Condiciones Comerciales'!B:M,4,FALSE))),N86) -> 2844.9 | P86: =(O86-10%*O86)/80% -> 3200.5125
A87: Alto Buzeta (MT) | B87: DEPARTAMENTO | C87: 3D1B | D87: 1001 | E87: 10 | F87: A | G87: 46.55 | H87: 2.26 | I87: Suroriente | J87: DOMINIO | K87: Disponible | N87: 3282 | O87: =IF(B87="DEPARTAMENTO",IF(C87="3D1B",N87*(100%-13%),N87*(100%-VLOOKUP(A87,'Condiciones Comerciales'!B:M,4,FALSE))),N87) -> 2855.34 | P87: =(O87-10%*O87)/80% -> 3212.2575
A88: Alto Buzeta (MT) | B88: DEPARTAMENTO | C88: 3D1B | D88: 1002 | E88: 10 | F88: A | G88: 47.06 | H88: 2.26 | I88: Suroriente | J88: DOMINIO | K88: Disponible | L88: B - 72 | N88: 3282 | O88: =IF(B88="DEPARTAMENTO",IF(C88="3D1B",N88*(100%-13%),N88*(100%-VLOOKUP(A88,'Condiciones Comerciales'!B:M,4,FALSE))),N88) -> 2855.34 | P88: =(O88-10%*O88)/80% -> 3212.2575
A89: Alto Buzeta (MT) | B89: DEPARTAMENTO | C89: 3D1B | D89: 1101 | E89: 11 | F89: A | G89: 46.55 | H89: 2.26 | I89: Suroriente | J89: DOMINIO | K89: Disponible | N89: 3288 | O89: =IF(B89="DEPARTAMENTO",IF(C89="3D1B",N89*(100%-13%),N89*(100%-VLOOKUP(A89,'Condiciones Comerciales'!B:M,4,FALSE))),N89) -> 2860.56 | P89: =(O89-10%*O89)/80% -> 3218.13
A90: Alto Buzeta (MT) | B90: DEPARTAMENTO | C90: 3D1B | D90: 1102 | E90: 11 | F90: A | G90: 47.06 | H90: 2.26 | I90: Suroriente | J90: DOMINIO | K90: Disponible | N90: 3288 | O90: =IF(B90="DEPARTAMENTO",IF(C90="3D1B",N90*(100%-13%),N90*(100%-VLOOKUP(A90,'Condiciones Comerciales'!B:M,4,FALSE))),N90) -> 2860.56 | P90: =(O90-10%*O90)/80% -> 3218.13
A91: Alto Buzeta (MT) | B91: DEPARTAMENTO | C91: 3D1B | D91: 1201 | E91: 12 | F91: A | G91: 46.55 | H91: 2.26 | I91: Suroriente | J91: DOMINIO | K91: Disponible | N91: 3295 | O91: =IF(B91="DEPARTAMENTO",IF(C91="3D1B",N91*(100%-13%),N91*(100%-VLOOKUP(A91,'Condiciones Comerciales'!B:M,4,FALSE))),N91) -> 2866.65 | P91: =(O91-10%*O91)/80% -> 3224.9812
A92: Alto Buzeta (MT) | B92: DEPARTAMENTO | C92: 3D1B | D92: 1202 | E92: 12 | F92: A | G92: 47.06 | H92: 2.26 | I92: Suroriente | J92: DOMINIO | K92: Disponible | L92: B - 74 | N92: 3295 | O92: =IF(B92="DEPARTAMENTO",IF(C92="3D1B",N92*(100%-13%),N92*(100%-VLOOKUP(A92,'Condiciones Comerciales'!B:M,4,FALSE))),N92) -> 2866.65 | P92: =(O92-10%*O92)/80% -> 3224.9812
A93: Alto Buzeta (MT) | B93: DEPARTAMENTO | C93: 3D1B | D93: 1301 | E93: 13 | F93: A | G93: 46.55 | H93: 2.26 | I93: Suroriente | J93: DOMINIO | K93: Disponible | N93: 3301 | O93: =IF(B93="DEPARTAMENTO",IF(C93="3D1B",N93*(100%-13%),N93*(100%-VLOOKUP(A93,'Condiciones Comerciales'!B:M,4,FALSE))),N93) -> 2871.87 | P93: =(O93-10%*O93)/80% -> 3230.8537
A94: Alto Buzeta (MT) | B94: DEPARTAMENTO | C94: 3D1B | D94: 1302 | E94: 13 | F94: A | G94: 47.06 | H94: 2.26 | I94: Suroriente | J94: DOMINIO | K94: Disponible | N94: 3301 | O94: =IF(B94="DEPARTAMENTO",IF(C94="3D1B",N94*(100%-13%),N94*(100%-VLOOKUP(A94,'Condiciones Comerciales'!B:M,4,FALSE))),N94) -> 2871.87 | P94: =(O94-10%*O94)/80% -> 3230.8537
A95: Alto Buzeta (MT) | B95: DEPARTAMENTO | C95: 3D1B | D95: 1401 | E95: 14 | F95: A | G95: 46.55 | H95: 2.26 | I95: Suroriente | J95: DOMINIO | K95: Disponible | N95: 3307 | O95: =IF(B95="DEPARTAMENTO",IF(C95="3D1B",N95*(100%-13%),N95*(100%-VLOOKUP(A95,'Condiciones Comerciales'!B:M,4,FALSE))),N95) -> 2877.09 | P95: =(O95-10%*O95)/80% -> 3236.7263
A96: Alto Buzeta (MT) | B96: DEPARTAMENTO | C96: 3D1B | D96: 1402 | E96: 14 | F96: A | G96: 47.06 | H96: 2.26 | I96: Suroriente | J96: DOMINIO | K96: Disponible | L96: B - 76 | N96: 3307 | O96: =IF(B96="DEPARTAMENTO",IF(C96="3D1B",N96*(100%-13%),N96*(100%-VLOOKUP(A96,'Condiciones Comerciales'!B:M,4,FALSE))),N96) -> 2877.09 | P96: =(O96-10%*O96)/80% -> 3236.7263
A97: Alto Buzeta (MT) | B97: DEPARTAMENTO | C97: 3D1B | D97: 1501 | E97: 15 | F97: A | G97: 46.55 | H97: 2.26 | I97: Suroriente | J97: DOMINIO | K97: Disponible | N97: 3313 | O97: =IF(B97="DEPARTAMENTO",IF(C97="3D1B",N97*(100%-13%),N97*(100%-VLOOKUP(A97,'Condiciones Comerciales'!B:M,4,FALSE))),N97) -> 2882.31 | P97: =(O97-10%*O97)/80% -> 3242.5987
A98: Alto Buzeta (MT) | B98: DEPARTAMENTO | C98: 3D1B | D98: 1502 | E98: 15 | F98: A | G98: 47.06 | H98: 2.26 | I98: Suroriente | J98: DOMINIO | K98: Disponible | N98: 3313 | O98: =IF(B98="DEPARTAMENTO",IF(C98="3D1B",N98*(100%-13%),N98*(100%-VLOOKUP(A98,'Condiciones Comerciales'!B:M,4,FALSE))),N98) -> 2882.31 | P98: =(O98-10%*O98)/80% -> 3242.5987
A99: Alto Buzeta (MT) | B99: DEPARTAMENTO | C99: 3D1B | D99: 1601 | E99: 16 | F99: A | G99: 46.55 | H99: 2.26 | I99: Suroriente | J99: DOMINIO | K99: Disponible | N99: 3319 | O99: =IF(B99="DEPARTAMENTO",IF(C99="3D1B",N99*(100%-13%),N99*(100%-VLOOKUP(A99,'Condiciones Comerciales'!B:M,4,FALSE))),N99) -> 2887.53 | P99: =(O99-10%*O99)/80% -> 3248.4713
A100: Alto Buzeta (MT) | B100: DEPARTAMENTO | C100: 3D1B | D100: 1602 | E100: 16 | F100: A | G100: 47.06 | H100: 2.26 | I100: Suroriente | J100: DOMINIO | K100: Disponible | L100: B - 78 | N100: 3319 | O100: =IF(B100="DEPARTAMENTO",IF(C100="3D1B",N100*(100%-13%),N100*(100%-VLOOKUP(A100,'Condiciones Comerciales'!B:M,4,FALSE))),N100) -> 2887.53 | P100: =(O100-10%*O100)/80% -> 3248.4713
A101: Alto Buzeta (MT) | B101: DEPARTAMENTO | C101: 3D1B | D101: 1701 | E101: 17 | F101: A | G101: 46.55 | H101: 2.26 | I101: Suroriente | J101: DOMINIO | K101: Disponible | N101: 3325 | O101: =IF(B101="DEPARTAMENTO",IF(C101="3D1B",N101*(100%-13%),N101*(100%-VLOOKUP(A101,'Condiciones Comerciales'!B:M,4,FALSE))),N101) -> 2892.75 | P101: =(O101-10%*O101)/80% -> 3254.3437
A102: Alto Buzeta (MT) | B102: DEPARTAMENTO | C102: 3D1B | D102: 1702 | E102: 17 | F102: A | G102: 47.06 | H102: 2.26 | I102: Suroriente | J102: DOMINIO | K102: Disponible | N102: 3325 | O102: =IF(B102="DEPARTAMENTO",IF(C102="3D1B",N102*(100%-13%),N102*(100%-VLOOKUP(A102,'Condiciones Comerciales'!B:M,4,FALSE))),N102) -> 2892.75 | P102: =(O102-10%*O102)/80% -> 3254.3437
A103: Alto Buzeta (MT) | B103: DEPARTAMENTO | C103: 3D1B | D103: 1801 | E103: 18 | F103: A | G103: 46.46 | H103: 2.26 | I103: Suroriente | J103: DOMINIO | K103: Disponible | N103: 3331 | O103: =IF(B103="DEPARTAMENTO",IF(C103="3D1B",N103*(100%-13%),N103*(100%-VLOOKUP(A103,'Condiciones Comerciales'!B:M,4,FALSE))),N103) -> 2897.97 | P103: =(O103-10%*O103)/80% -> 3260.2162
A104: Alto Buzeta (MT) | B104: DEPARTAMENTO | C104: 3D1B | D104: 1802 | E104: 18 | F104: A | G104: 47.06 | H104: 2.26 | I104: Suroriente | J104: DOMINIO | K104: Disponible | L104: B - 80 | N104: 3331 | O104: =IF(B104="DEPARTAMENTO",IF(C104="3D1B",N104*(100%-13%),N104*(100%-VLOOKUP(A104,'Condiciones Comerciales'!B:M,4,FALSE))),N104) -> 2897.97 | P104: =(O104-10%*O104)/80% -> 3260.2162
A105: Alto Buzeta (MT) | B105: DEPARTAMENTO | C105: 3D1B | D105: 1901 | E105: 19 | F105: A | G105: 46.55 | H105: 2.26 | I105: Suroriente | J105: DOMINIO | K105: Disponible | N105: 3337 | O105: =IF(B105="DEPARTAMENTO",IF(C105="3D1B",N105*(100%-13%),N105*(100%-VLOOKUP(A105,'Condiciones Comerciales'!B:M,4,FALSE))),N105) -> 2903.19 | P105: =(O105-10%*O105)/80% -> 3266.0887
...

Sheet Resumen
B2: UNIDADES DISPONIBLES POR TIPOLOGÍA
B3: Cuenta de Numero | C3: Etiquetas de columna
B4: PROYECTO | C4: 1D1BS | D4: 1D1BSg | E4: 1D1B | F4: 2D1B | G4: 2D2B | H4: 2D2BM | I4: 2Dg1B | J4: 3D1B | K4: BODEGA | L4: ESTACIONAMIENTO | M4: ESTACIONAMIENTO LC | N4: LOCAL COMERCIAL
B5: Alto Buzeta (MT) | C5: 2 | D5: 3 | E5: 1 | F5: 3 | I5: 70 | J5: 28 | K5: 59 | L5: 102 | M5: 2 | N5: 1
B6: Cáceres | F6: 16 | I6: 8 | J6: 29 | K6: 18 | L6: 13 | N6: 4
B7: Distrito Centro | E7: 19 | F7: 91 | H7: 52 | K7: 70 | L7: 141
B8: General Mackenna | E8: 18 | F8: 83 | H8: 28 | I8: 33 | J8: 14 | K8: 67 | L8: 52
B9: Jardines de Alvarado | E9: 5 | F9: 28 | I9: 10 | J9: 49 | K9: 1 | L9: 173
B10: Mirador Mapocho | E10: 54 | F10: 6 | H10: 6 | I10: 9 | J10: 4 | K10: 6 | L10: 86 | N10: 4
B11: Pintor Cicarelli I (PC I) | F11: 51 | H11: 47 | I11: 13 | J11: 100 | K11: 39 | L11: 120 | M11: 12 | N11: 18
B12: Pintor Cicarelli II | F12: 16 | I12: 7 | J12: 6 | L12: 23
B13: Plaza Cervantes I | F13: 10 | J13: 4 | L13: 7
B14: Plaza Cervantes II | F14: 5 | I14: 1 | L14: 14
B15: Plaza Quilicura | F15: 31 | K15: 21 | L15: 22
B16: SERRANO TORRE A | E16: 38 | F16: 92 | H16: 37 | I16: 21 | J16: 11 | K16: 99 | L16: 148
B17: Trinidad III | G17: 1 | H17: 2 | K17: 2 | L17: 5
B18: Vista Costanera | F18: 13 | I18: 2 | K18: 1 | L18: 40
B19: Vista Llacolén A | C19: 16 | E19: 45 | H19: 55 | I19: 89 | L19: 111
B20: Vista Llacolén B2 | E20: 1 | H20: 18 | I20: 30 | L20: 55
B21: Vista Reloncaví | F21: 22 | I21: 25 | J21: 33 | L21: 46
B22: Vistamar | F22: 71 | H22: 54 | I22: 23 | J22: 8 | K22: 66 | L22: 93 | N22: 4
B23: Total general | C23: 18 | D23: 3 | E23: 181 | F23: 538 | G23: 1 | H23: 299 | I23: 341 | J23: 286 | K23: 449 | L23: 1251 | M23: 14 | N23: 31
B26: VALORES DE PRECIO DE VENTA DESDE UF
B27: Mín. de Precio VENTA | C27: Etiquetas de columna
B28: PROYECTO | C28: 1D1BS | D28: 1D1BSg | E28: 1D1B | F28: 2D1B | G28: 2D2B | H28: 2D2BM | I28: 2Dg1B | J28: 3D1B | K28: BODEGA | L28: ESTACIONAMIENTO | M28: ESTACIONAMIENTO LC | N28: LOCAL COMERCIAL
B29: Alto Buzeta (MT) | C29: 2054.3625 | D29: 2474.55 | E29: 2603.1375 | F29: 2742.8625 | I29: 2968.65 | J29: 3130.0425 | K29: 33.75 | L29: 393.75 | M29: 393.75 | N29: 1515.375
B30: Cáceres | F30: 2628.45 | I30: 2829.9375 | J30: 2900.8125 | K30: 45 | L30: 315 | N30: 4295.25
B31: Distrito Centro | E31: 2548.4062 | F31: 2672.7188 | H31: 3032.2687 | K31: 22.5 | L31: 337.5
B32: General Mackenna | E32: 2208.9375 | F32: 2348.55 | H32: 2604.825 | I32: 2523.5437 | J32: 2643.075 | K32: 56.25 | L32: 337.5
B33: Jardines de Alvarado | E33: 2261.8912 | F33: 2339.2125 | I33: 2585.8575 | J33: 2613.2625 | K33: 232.875 | L33: 281.25
B34: Mirador Mapocho | E34: 2400.8737 | F34: 2551.5 | H34: 2860.3125 | I34: 2783.3625 | J34: 2907.9 | K34: 56.25 | L34: 393.75 | N34: 3244.5
B35: Pintor Cicarelli I (PC I) | F35: 2771.82 | H35: 3059.5725 | I35: 3015.5287 | J35: 3052.7213 | K35: 56.25 | L35: 360 | M35: 360 | N35: 1798.875
B36: Pintor Cicarelli II | F36: 2805.0975 | I36: 3026.295 | J36: 3161.3625 | L36: 427.5
B37: Plaza Cervantes I | F37: 2405.7 | J37: 2688.1875 | L37: 281.25
B38: Plaza Cervantes II | F38: 2509.9875 | I38: 2606.175 | L38: 337.5
B39: Plaza Quilicura | F39: 2447.28 | K39: 45 | L39: 225
B40: SERRANO TORRE A | E40: 2534.2875 | F40: 2757.0375 | H40: 3231.9 | I40: 3053.7 | J40: 3298.725 | K40: 33.75 | L40: 337.5
B41: Trinidad III | G41: 2589.975 | H41: 2627.4375 | K41: 78.75 | L41: 371.25
B42: Vista Costanera | F42: 2310.66 | I42: 2492.82 | K42: 56.25 | L42: 337.5
B43: Vista Llacolén A | C43: 2485.6875 | E43: 2765.1375 | H43: 3273.4125 | I43: 3043.575 | L43: 253.125
B44: Vista Llacolén B2 | E44: 2633.5125 | H44: 3213.675 | I44: 3091.1625 | L44: 253.125
B45: Vista Reloncaví | F45: 2657.8125 | I45: 2940.3 | J45: 3106.62 | L45: 337.5
B46: Vistamar | F46: 2386.89 | H46: 3225.825 | I46: 2569.05 | J46: 3109.3875 | K46: 47.25 | L46: 337.5 | N46: 4017.375
B47: Total general | C47: 2054.3625 | D47: 2474.55 | E47: 2208.9375 | F47: 2310.66 | G47: 2589.975 | H47: 2604.825 | I47: 2492.82 | J47: 2613.2625 | K47: 22.5 | L47: 225 | M47: 360 | N47: 1515.375
B50: VALORES PROMEDIOS DE PRECIO DE VENTA
B51: Promedio de Precio VENTA | C51: Etiquetas de columna
B52: PROYECTO | C52: 1D1BS | D52: 1D1BSg | E52: 1D1B | F52: 2D1B | G52: 2D2B | H52: 2D2BM | I52: 2Dg1B | J52: 3D1B | K52: BODEGA | L52: ESTACIONAMIENTO | M52: ESTACIONAMIENTO LC | N52: LOCAL COMERCIAL
B53: Alto Buzeta (MT) | C53: 2131.3125 | D53: 2486.7 | E53: 2603.1375 | F53: 2788.0875 | I53: 3156.5555 | J53: 3229.2458 | K53: 117.97246 | L53: 394.85294 | M53: 393.75 | N53: 1515.375
B54: Cáceres | F54: 2704.5141 | I54: 2933.5922 | J54: 2988.0272 | K54: 78.25 | L54: 327.11538 | N54: 4539.6562
B55: Distrito Centro | E55: 2601.8556 | F55: 2834.5141 | H55: 3167.5413 | K55: 82.832143 | L55: 388.96277
B56: General Mackenna | E56: 2277.575 | F56: 2455.0394 | H56: 2711.1054 | I56: 2632.9909 | J56: 2706.8705 | K56: 73.880597 | L56: 379.6875
B57: Jardines de Alvarado | E57: 2341.5615 | F57: 2482.9489 | I57: 2649.0847 | J57: 2702.0491 | K57: 232.875 | L57: 310.24639
B58: Mirador Mapocho | E58: 2493.0431 | F58: 2648.025 | H58: 2918.3625 | I58: 2885.2875 | J58: 2991.6844 | K58: 93.75 | L58: 394.32558 | N58: 3742.0312
B59: Pintor Cicarelli I (PC I) | F59: 2830.7369 | H59: 3168.7344 | I59: 3036.0825 | J59: 3169.9853 | K59: 88.846154 | L59: 432.375 | M59: 360 | N59: 2641.75
B60: Pintor Cicarelli II | F60: 2852.9951 | I60: 3040.5568 | J60: 3212.0944 | L60: 430.43478
B61: Plaza Cervantes I | F61: 2498.85 | J61: 2719.8281 | L61: 329.46429
B62: Plaza Cervantes II | F62: 2551.5 | I62: 2606.175 | L62: 337.5
B63: Plaza Quilicura | F63: 2506.2692 | K63: 80.839286 | L63: 298.22727
B64: SERRANO TORRE A | E64: 2682.8586 | F64: 2866.5526 | H64: 3299.628 | I64: 3134.1214 | J64: 3328.2716 | K64: 73.75 | L64: 337.5
B65: Trinidad III | G65: 2589.975 | H65: 2636.55 | K65: 78.75 | L65: 371.25
B66: Vista Costanera | F66: 2346.9092 | I66: 2537.865 | K66: 56.25 | L66: 369.675
B67: Vista Llacolén A | C67: 2620.7297 | E67: 2894.715 | H67: 3396.7166 | I67: 3164.4265 | L67: 363.34459
B68: Vista Llacolén B2 | E68: 2633.5125 | H68: 3348.3938 | I68: 3190.1175 | L68: 347.72727
B69: Vista Reloncaví | F69: 2784.1909 | I69: 3051.3105 | J69: 3161.1 | L69: 348.50543
B70: Vistamar | F70: 2500.8351 | H70: 3297.8063 | I70: 2633.1417 | J70: 3175.0734 | K70: 84.357955 | L70: 370.16129 | N70: 4341.0938
B71: Total general | C71: 2566.35 | D71: 2486.7 | E71: 2619.9513 | F71: 2671.48 | G71: 2589.975 | H71: 3209.3484 | I71: 3027.005 | J71: 3051.7947 | K71: 84.983853 | L71: 366.57284 | M71: 364.82143 | N71: 3211.5484
B74: EstadoInmueble | C74: Arrendado
B75: UNIDADES CON ARRENDATARIO INCLUIDO ASSETPLAN
B76: Cuenta de Numero | C76: Etiquetas de columna
B77: PROYECTO | C77: 2D1B | D77: 2D2BM | E77: 2Dg1B | F77: 3D1B | G77: ESTACIONAMIENTO
B78: Jardines de Alvarado | C78: 7 | E78: 9 | F78: 48 | G78: 58
B79: Mirador Mapocho | E79: 1 | G79: 28
B80: Pintor Cicarelli I (PC I) | C80: 13 | D80: 12 | E80: 6 | F80: 27 | G80: 33
B81: Plaza Cervantes I | C81: 5 | F81: 4 | G81: 3
B82: Plaza Quilicura | G82: 6
B83: Vista Reloncaví | F83: 20 | G83: 5
B84: Total general | C84: 25 | D84: 12 | E84: 16 | F84: 99 | G84: 133
B87: TIPO | C87: DEPARTAMENTO
B88: DEPTOS DISPONIBLES POR PROYECTO
B89: Cuenta de Numero | C89: Etiquetas de columna
B90: PROYECTO | C90: Disponible | D90: En Recolocación | E90: Arrendado | F90: Total | G90: Entega | H90: Comuna
B91: Alto Buzeta (MT) | C91: 97 | D91: 10 | F91: 107 | G91: =VLOOKUP(B91,'Condiciones Comerciales'!$B$4:$D$21,2,FALSE) -> Inmediata | H91: =VLOOKUP(B91,'Condiciones Comerciales'!$B$4:$D$21,3,FALSE) -> Cerrillos
B92: Cáceres | C92: 50 | D92: 3 | F92: 53 | G92: =VLOOKUP(B92,'Condiciones Comerciales'!$B$4:$D$21,2,FALSE) -> Inmediata | H92: =VLOOKUP(B92,'Condiciones Comerciales'!$B$4:$D$21,3,FALSE) -> Rancagua
B93: Distrito Centro | C93: 162 | F93: 162 | G93: =VLOOKUP(B93,'Condiciones Comerciales'!$B$4:$D$21,2,FALSE) -> 2029 | H93: =VLOOKUP(B93,'Condiciones Comerciales'!$B$4:$D$21,3,FALSE) -> Chillán
B94: General Mackenna | C94: 176 | F94: 176 | G94: =VLOOKUP(B94,'Condiciones Comerciales'!$B$4:$D$21,2,FALSE) -> 2029 | H94: =VLOOKUP(B94,'Condiciones Comerciales'!$B$4:$D$21,3,FALSE) -> Temuco
B95: Jardines de Alvarado | C95: 13 | D95: 15 | E95: 64 | F95: 92 | G95: =VLOOKUP(B95,'Condiciones Comerciales'!$B$4:$D$21,2,FALSE) -> Inmediata | H95: =VLOOKUP(B95,'Condiciones Comerciales'!$B$4:$D$21,3,FALSE) -> Independencia
B96: Mirador Mapocho | C96: 61 | D96: 17 | E96: 1 | F96: 79 | G96: =VLOOKUP(B96,'Condiciones Comerciales'!$B$4:$D$21,2,FALSE) -> Inmediata | H96: =VLOOKUP(B96,'Condiciones Comerciales'!$B$4:$D$21,3,FALSE) -> Quinta Normal
B97: Pintor Cicarelli I (PC I) | C97: 149 | D97: 4 | E97: 58 | F97: 211 | G97: =VLOOKUP(B97,'Condiciones Comerciales'!$B$4:$D$21,2,FALSE) -> Pre-entrega | H97: =VLOOKUP(B97,'Condiciones Comerciales'!$B$4:$D$21,3,FALSE) -> San Joaquín
B98: Pintor Cicarelli II | C98: 13 | D98: 16 | F98: 29 | G98: =VLOOKUP(B98,'Condiciones Comerciales'!$B$4:$D$21,2,FALSE) -> Inmediata | H98: =VLOOKUP(B98,'Condiciones Comerciales'!$B$4:$D$21,3,FALSE) -> San Joaquín
B99: Plaza Cervantes I | C99: 4 | D99: 1 | E99: 9 | F99: 14 | G99: =VLOOKUP(B99,'Condiciones Comerciales'!$B$4:$D$21,2,FALSE) -> Inmediata | H99: =VLOOKUP(B99,'Condiciones Comerciales'!$B$4:$D$21,3,FALSE) -> La Cisterna
B100: Plaza Cervantes II | C100: 6 | F100: 6 | G100: =VLOOKUP(B100,'Condiciones Comerciales'!$B$4:$D$21,2,FALSE) -> Inmediata | H100: =VLOOKUP(B100,'Condiciones Comerciales'!$B$4:$D$21,3,FALSE) -> La Cisterna
B101: Plaza Quilicura | C101: 17 | D101: 14 | F101: 31 | G101: =VLOOKUP(B101,'Condiciones Comerciales'!$B$4:$D$21,2,FALSE) -> Inmediata | H101: =VLOOKUP(B101,'Condiciones Comerciales'!$B$4:$D$21,3,FALSE) -> Quilicura
B102: SERRANO TORRE A | C102: 199 | F102: 199 | G102: =VLOOKUP(B102,'Condiciones Comerciales'!$B$4:$D$21,2,FALSE) -> 2028 | H102: =VLOOKUP(B102,'Condiciones Comerciales'!$B$4:$D$21,3,FALSE) -> Puerto Montt
B103: Trinidad III | C103: 2 | D103: 1 | F103: 3 | G103: =VLOOKUP(B103,'Condiciones Comerciales'!$B$4:$D$21,2,FALSE) -> Inmediata | H103: =VLOOKUP(B103,'Condiciones Comerciales'!$B$4:$D$21,3,FALSE) -> La Cisterna
B104: Vista Costanera | C104: 15 | F104: 15 | G104: =VLOOKUP(B104,'Condiciones Comerciales'!$B$4:$D$21,2,FALSE) -> Inmediata | H104: =VLOOKUP(B104,'Condiciones Comerciales'!$B$4:$D$21,3,FALSE) -> Renca
B105: Vista Llacolén A | C105: 205 | F105: 205 | G105: =VLOOKUP(B105,'Condiciones Comerciales'!$B$4:$D$21,2,FALSE) -> 2029 | H105: =VLOOKUP(B105,'Condiciones Comerciales'!$B$4:$D$21,3,FALSE) -> Concepción
B106: Vista Llacolén B2 | C106: 49 | F106: 49 | G106: =VLOOKUP(B106,'Condiciones Comerciales'!$B$4:$D$21,2,FALSE) -> 2028 | H106: =VLOOKUP(B106,'Condiciones Comerciales'!$B$4:$D$21,3,FALSE) -> Concepción
B107: Vista Reloncaví | C107: 42 | D107: 18 | E107: 20 | F107: 80 | G107: =VLOOKUP(B107,'Condiciones Comerciales'!$B$4:$D$21,2,FALSE) -> Inmediata | H107: =VLOOKUP(B107,'Condiciones Comerciales'!$B$4:$D$21,3,FALSE) -> Puerto Montt
B108: Vistamar | C108: 156 | F108: 156 | G108: =VLOOKUP(B108,'Condiciones Comerciales'!$B$4:$D$21,2,FALSE) -> 2029 | H108: =VLOOKUP(B108,'Condiciones Comerciales'!$B$4:$D$21,3,FALSE) -> Coquimbo
B109: Total | C109: 1416 | D109: 99 | E109: 152 | F109: 1667
...

Sheet Condiciones Comerciales
Q1: CHECK LIST PARA VB DE PROMESAS MAESTRA BROKERS
B2: Condiciones ABRIL 2026
B3: PROYECTO | C3: ENTREGA | D3: COMUNA | E3: Descuento Base | F3: Dcto Adicional | G3: Giftcard | H3: Upfront | I3: Pie en cuotas | J3: UPAGO Cuotas | K3: Cuota desde | L3: Certificado Pago | M3: Mutuo UPAGO | AA3: PROYECTO | AB3: RAZÓN SOCIAL | AC3: RUT
A4: PD | B4: Vista Llacolén B2 | C4: 2028 | D4: Concepción | E4: 0.1 | H4: 0.02 | I4: =20%-L4-H4 -> 0.08 | J4: 21 | K4: UF 7,0 | L4: 0.1 | M4: No | Q4: ENTREGA INMEDIATA | V4: ENTREGA FUTURA | AA4: Aldunate | AB4: MAESTRA SANTA ROSA SPA | AC4: 76409319-4
A5: PD | B5: Vista Llacolén A | C5: 2029 | D5: Concepción | E5: 0.1 | H5: 0.02 | I5: =20%-L5-H5 -> 0.08 | J5: 34 | K5: UF 7,0 | L5: 0.1 | M5: No | AA5: Alto Buzeta (MT) | AB5: MAESTRA TRAVESIA SPA | AC5: 77700583-9
B6: SERRANO TORRE A | C6: 2028 | D6: Puerto Montt | E6: 0.1 | H6: 0.02 | I6: =20%-L6-H6 -> 0.08 | J6: 21 | K6: UF 7,0 | L6: 0.1 | M6: No | Q6: 1 | R6: RUT escaneado | V6: 1 | W6: RUT escaneado | AA6: Apostol Santiago | AB6: MAESTRA ENTRE RIOS SPA | AC6: 76411296-2
A7: PD | B7: General Mackenna | C7: 2029 | D7: Temuco | E7: 0.15 | G7: 500000 | H7: 0.01 | I7: =20%-L7-H7 -> 0.09 | J7: 35 | K7: UF 7,0 | L7: 0.1 | M7: No | Q7: 2 | R7: Reserva Firmada y pagada | V7: 2 | W7: Liquidaciones de Sueldo | AA7: Cáceres | AB7: MAESTRA PROYECTOS SPA | AC7: 77274888-4
A8: PD | B8: Vistamar | C8: 2029 | D8: Coquimbo | E8: 0.1 | F8: 2% SurOriente | H8: 0.02 | I8: =20%-L8-H8 -> 0.08 | J8: 34 | K8: UF 7,0 | L8: 0.1 | M8: No | Q8: 3 | R8: Aprobación de Crédito | V8: 3 | W8: Reserva Firmada y pagada | AA8: General Mackenna | AB8: VISTA LLACOLEN SPA | AC8: 77684759-3
B9: Distrito Centro | C9: 2029 | D9: Chillán | E9: 0.15 | G9: 500000 | H9: 0.01 | I9: =20%-L9-H9 -> 0.09 | J9: 36 | K9: UF 7,0 | L9: 0.1 | M9: No | Q9: 4 | R9: Promesa firmada | V9: 4 | W9: Pre-Aprobación de Crédito + Infocheck Crédito Full | AA9: Jardines de Alvarado | AB9: MAESTRA DON RODRIGO SPA | AC9: 76416917-4
B10: Pintor Cicarelli I (PC I) | C10: Pre-entrega | D10: San Joaquín | E10: 0.13 | G10: GOP | H10: 0.02 | I10: =20%-L10-H10 -> 0.03 | J10: 3 | K10: UF 7,0 | L10: 0.15 | M10: Creditú | Q10: 5 | R10: Mutuo y GOP pagado (si aplica) | V10: 5 | W10: Promesa firmada | AA10: Mirador Mapocho | AB10: MAESTRA PROYECTOS SPA | AC10: 77274888-4
B11: Alto Buzeta (MT) | C11: Inmediata | D11: Cerrillos | E11: 0.1 | F11: 3% 3D | G11: GOP | I11: 0.1 | J11: 60 | L11: 0.1 | M11: Creditú | Q11: 6 | R11: Mutuo con pago automático Upago | V11: 6 | W11: Upfront pagado | AA11: Pintor Cicarelli I (PC I) | AB11: PINTOR CICARELLI I SPA | AC11: 77684746-1
A12: PD | B12: Cáceres | C12: Inmediata | D12: Rancagua | E12: 0.1 | G12: GOP | I12: 0.1 | J12: 60 | L12: 0.1 | M12: Max 10% | Q12: 7 | R12: Certificado de Pago (si aplica) | V12: 7 | W12: Suscripción de pago automático Upago | AA12: Pintor Cicarelli II | AB12: MAESTRA PROYECTOS SPA | AC12: 77274888-4
B13: Jardines de Alvarado | C13: Inmediata | D13: Independencia | E13: 0.13 | G13: GOP | I13: 0.1 | J13: 60 | L13: 0.1 | M13: Max 10% | Q13: 8 | R13: Promoción Firmada (si aplica) | V13: 8 | W13: Promoción Firmada (si aplica) | AA13: Plaza Cervantes I | AB13: MAESTRA SANTA ROSA SPA | AC13: 76409319-4
A14: PD | B14: Mirador Mapocho | C14: Inmediata | D14: Quinta Normal | E14: 0.1 | F14: 3% 1D | G14: GOP | I14: 0.1 | J14: 60 | L14: 0.1 | M14: Max 10% | Q14: 9 | R14: EETT firmada | V14: 9 | W14: EETT firmada | AA14: Plaza Cervantes II | AB14: MAESTRA SANTA ROSA SPA | AC14: 76409319-4
A15: PD | B15: Pintor Cicarelli II | C15: Inmediata | D15: San Joaquín | E15: 0.13 | G15: GOP | I15: 0.1 | J15: 60 | L15: 0.1 | M15: Max 10% | Q15: 10 | R15: PEP firmado | V15: 10 | W15: PEP firmado | AA15: Plaza Quilicura | AB15: MAESTRA PROYECTOS SPA | AC15: 77274888-4
B16: Plaza Cervantes I | C16: Inmediata | D16: La Cisterna | E16: 0.1 | G16: GOP | I16: 0.1 | J16: 60 | L16: 0.1 | M16: Max 10% | Q16: 11 | R16: Pie pagado | V16: 11 | W16: Reserva Contabilizada | AA16: SERRANO TORRE A | AB16: INVERSIONES IGNACIO SERRANO SPA | AC16: 77956043-0
B17: Plaza Cervantes II | C17: Inmediata | D17: La Cisterna | E17: 0.1 | G17: GOP | I17: 0.1 | J17: 60 | L17: 0.1 | M17: Max 10% | Q17: 12 | R17: Reserva Contabilizada | V17: 12 | W17: Promesa firmada por representantes de Maestra | AA17: Trinidad III | AB17: MAESTRA PROYECTOS SPA | AC17: 77274888-4
A18: PD | B18: Plaza Quilicura | C18: Inmediata | D18: Quilicura | E18: 0.1 | F18: 2% 2D (36m2) | G18: GOP | I18: 0.1 | J18: 60 | L18: 0.1 | M18: Max 10% | AA18: Vista Costanera | AB18: MAESTRA QUILPUE DOS SPA | AC18: 76489618-1
B19: Trinidad III | C19: Inmediata | D19: La Cisterna | E19: 0.1 | G19: GOP | I19: 0.1 | J19: 60 | L19: 0.1 | M19: Max 10% | AA19: Vista Llacolén A | AB19: VISTA LLACOLEN SPA | AC19: 77684759-3
B20: Vista Costanera | C20: Inmediata | D20: Renca | E20: 0.12 | G20: GOP | I20: 0.1 | J20: 60 | L20: 0.1 | M20: Max 10% | R20: Pago de Reserva Webpay: | AA20: Vista Llacolén B2 | AB20: VISTA LLACOLEN SPA | AC20: 77684759-3
A21: PD | B21: Vista Reloncaví | C21: Inmediata | D21: Puerto Montt | E21: 0.1 | F21: 2% 3D | G21: GOP | I21: 0.1 | J21: 60 | L21: 0.1 | M21: Max 10% | R21: https://www.webpay.cl/company/32764 | AA21: Vista Reloncaví | AB21: MAESTRA CONDELL S.A. | AC21: 76113459-0
AA22: Vistamar | AB22: MAESTRA VISTAMAR SPA | AC22: 77684739-9
B23: PARA TODAS LAS VENTAS APLICA CERTIFICADO DE PAGO DE 10% (Bono Pie) | R23: Portal de Pago UPago: | V23: Y excepcionalmente para pago de Pie:
B24: Recordar que la cuota mínima en todos los casos para Proyectos de Entrega Futura es de UF 7 | R24: https://pay.upago.cl/go/inmobiliaria-maestra | V24: https://www.webpay.cl/company/33138
B25: Promoción Entrega Inmediata: Devolución de $800.000 por concepto de Gastos Operacionales ó pago de Gastos Comunes (Efectivo 30 días post CBR).
B26: Jardines de Alvarado: Bajan los estacionamientos!! 2 x UF 400 | 1 x UF 250 | R26: TRANSFERENCIA (sólo casos excepcionales) | V26: VALE VISTA (sólo casos excepcionales)
B27: Plaza Quilicura: Se deben vender todos los departamentos con estacionamiento de manera obligatoria; Estacionamientos bajan a UF 250 (Precio anterior UF 290) | R27: 76.849.520-3 | V27: Nominativo a nombre y RUT de la SpA del Proyecto
B28: Vista Costanera: Bajan los estacionamientos a 2 x UF 500 | R28: MAESTRA S.A. | V28: Enviar correo de pago a GERALDINE.SALAS@MAESTRA.CL
B29: Promoción Arriendo Garantizado (gestionado por Assetplan): | R29: SCOTIABANK | V29: Enviar documento a:
B30: Jardines de Alvarado: solo tipología 3D1B (con descuento máximo de venta de 10%) | R30: CTA CTE 1167294 | W30: Edificio Work Plaza La Dehesa
B31: Mirador Mapocho: solo tipología 1D1B (con descuento máximo de venta de 10%) | R31: CANAL.BROKER@maestra.cl | W31: Av. La Dehesa N° 222, Torre A, Piso 5, Lo Barnechea
B32: Pintor Cicarelli I: solo tipología 3D1B (con descuento máximo de venta de 10%)
B33: Promoción Arrendatario Incluido (gestionado por Assetplan): 50% de descuento en el costo de administración por 1 años (3,5%)
B35: PD
B36: Proyecto Destacado del mes
B38: FECHA INGRESO CARPETA RECEPCIÓN MUNICIPAL

Sheet Calculadora BP+Mutuo
C2: SÓLO MODIFICAR ESTAS CELDAS | D2: XXX | K2: Plantas
C4: Simulación con Certificado de Pago (Bono Pie), Crédito Hipotecario y cuotas para pago de Pie | K4: 1D1BS | L4: Departamento Studio pequeño
C7: =+D51 -> Alto Buzeta (MT) | D7: =VLOOKUP(C7,'Condiciones Comerciales'!$B$3:$C$21,2,FALSE) -> Inmediata
D9: Precio de Lista
C10: Departamento 301 (2D1B) | D10: 3319
C11: Estacionamiento | D11: 0
C12: Bodega | D12: 0
D13: =SUM(D10:D12) -> 3319
C15: Descuento Venta: | D15: 0.13
D17: Precio de Venta | K17: 1D1BSg | L17: Departamento Studio grande
C18: Departamento | D18: =D10*(100%-D15) -> 2887.53
C19: Estacionamiento | D19: =D11 -> 0
C20: Bodega | D20: =D12 -> 0
C21: Total | D21: =SUM(D18:D20) -> 2887.53
F22: Imagen referencial
C23: Pie Total: | D23: 0.05 | G23: UF: | H23: 39841.72
C25: Reserva por $ 100.000: | D25: =100000/H23 -> 2.5099318 | E25: =D25/$D$21 -> 0.00086923142
C26: Pago inicial Upfront: | D26: =VLOOKUP(C7,'Condiciones Comerciales'!B3:M21,7,FALSE) -> 0
C27: Upfront en UF: | D27: =D21*D26 -> 0 | E27: =D27/$D$21 -> 0 | F27: =+D27*H23 -> 0
C28: * Saldo de Pie por pagar: | D28: =IF(D23=0%,0,D21*D23-D25-D27) -> 141.86657 | E28: =D28/$D$21 -> 0.049130769 | F28: =IF(D7="Inmediata","* Mutuo Maestra 60 cuotas de:", "* Cuotas sin interés desde:") -> * Mutuo Maestra 60 cuotas de: | G28: =IF(D7="Inmediata",-PMT(5%/12,60,D28),7) -> 2.6771972 | H28: =+G28*H23 -> 106664.14
C29: Crédito Hipotecario + Cert. Pago: | D29: =+D21*(100%-D23) -> 2743.1535 | E29: =D29/$D$21 -> 0.95 | F29: =IF(G28=7,"Cuotas de UF 7:","") | G29: =IF(G28=7,ROUNDDOWN(D28/7,0),"")
F30: =IF(G28=7,"Diferencia cuota adicional:","") | G30: =IF(G28=7,D28-(G28*G29),"") | K30: 1D1B | L30: Departamento de 1 dormitorio y 1 baño
C31: Certificado de Pago: | D31: 0 | F31: =IF(G28=7,"Máximo de cuotas Proyecto:","") | G31: =IF(G28=7,VLOOKUP(C7,'Condiciones Comerciales'!B3:J21,9,FALSE),"") | H31: =IF(G28=7,IF(G31>=(G29+1),"OK","No Cumple"),"")
F32: =IF(H31="No Cumple","Debe pagar cuotas de:","") | G32: =IF(H31="No Cumple",D28/G31,"") | H32: =IF(F32<>"",G32*H23,"")
C33: Crédito Hipotecario: | D33: =100%-D23-D31 -> 0.95
C35: Precio de Venta (Tasación): | D35: =D29/D33 -> 2887.53
C36: Certificado de Pago en UF: | D36: =D35-D37-D38 -> 0 | E36: =D36/$D$35 -> 0
C37: Pie pagado (Reserva+Upfront+Mutuo): | D37: =D25+D27+D28 -> 144.3765 | E37: =D37/$D$35 -> 0.05
C38: * Crédito Hipotecario | D38: =D35*D33 -> 2743.1535 | E38: =D38/$D$35 -> 0.95 | F38: * 300 Dividendos a tasa 4,0%: | G38: =PMT(4%/12,300,-D38) -> 14.479375 | H38: =+G38*H23 -> 576883.19
C41: Beneficios Maestra - Promociones:
C43: Devolución de $ 800.000 por GOP: | D43: =800000/H23 -> 20.079454 | F43: A los 30 días del CBR | K43: 2D1B | L43: Departamento de 2 dormitorios y 1 baño
C44: ó
C45: Arriendo Asegurados por 24 meses: | D45: =340000/H23 -> 8.5337681 | F45: Sólo para PC1, JdeA y MM* | G45: *ver AG_Assetplan
C51: PROYECTO | D51: Alto Buzeta (MT)
C53: Torre/Orientación/Unidad | D53: Precio de Lista
C54: 11 | D54: 80
C55: (blank) | D55: 80
C56: DOMINIO | D56: 80 | K56: 2D2B | L56: Departamento de 2 dormitorios y 2 baños
C57: BODEGA | D57: 80
C58: ESTACIONAMIENTO | D58: 350
C59: 117 | D59: 350
C60: (blank) | D60: 350
C61: DOMINIO | D61: 350
C62: ESTACIONAMIENTO | D62: 350
C63: 118 | D63: 350
C64: (blank) | D64: 350
C65: DOMINIO | D65: 350
C66: ESTACIONAMIENTO | D66: 350
C67: 111 | D67: 350
C68: (blank) | D68: 350
C69: DOMINIO | D69: 350 | K69: 2D2BM | L69: Departamento de 2 dormitorios y 2 baños Mariposa
C70: ESTACIONAMIENTO | D70: 350
C71: 119 | D71: 350
C72: (blank) | D72: 350
C73: DOMINIO | D73: 350
C74: ESTACIONAMIENTO | D74: 350
C75: 113 | D75: 350
C76: (blank) | D76: 350
C77: DOMINIO | D77: 350
C78: ESTACIONAMIENTO | D78: 350
C79: 114 | D79: 350
C80: (blank) | D80: 350
C81: DOMINIO | D81: 350
C82: ESTACIONAMIENTO | D82: 350 | K82: 2Dg1B | L82: Departamento de 2 dormitorios grandes y 2 baños
C83: 110 | D83: 350
C84: (blank) | D84: 350
C85: DOMINIO | D85: 350
C86: ESTACIONAMIENTO | D86: 350
C87: 112 | D87: 350
C88: (blank) | D88: 350
C89: DOMINIO | D89: 350
C90: ESTACIONAMIENTO | D90: 350
C91: 115 | D91: 350
C92: (blank) | D92: 350
C93: DOMINIO | D93: 350
C94: ESTACIONAMIENTO | D94: 350
C95: 116 | D95: 350 | K95: 3D1B | L95: Departamento de 3 dormitorios y 1 baño
C96: (blank) | D96: 350
C97: DOMINIO | D97: 350
C98: ESTACIONAMIENTO | D98: 350
C99: 1118 | D99: 3084
C100: A | D100: 3084
C101: Surponiente | D101: 3084
C102: 2Dg1B | D102: 3084
C103: 1109 | D103: 3120
C104: A | D104: 3120
C105: Norponiente | D105: 3120
C106: 2Dg1B | D106: 3120
C107: 1108 | D107: 3120
C108: A | D108: 3120 | K108: 3D2B | L108: Departamento de 3 dormitorios y 2 baños
C109: Norponiente | D109: 3120
C110: 2Dg1B | D110: 3120
C111: 1113 | D111: 3144
C112: A | D112: 3144
C113: Nororiente | D113: 3144
C114: 2Dg1B | D114: 3144
C115: 1101 | D115: 3288
C116: A | D116: 3288
C117: Suroriente | D117: 3288
C118: 3D1B | D118: 3288
...

Sheet AG_Assetplan
A29: * EL COSTO DEL AG ES DE UN 3% MENOS EN EL DESCUENTO DE VENTA

Sheet Inversionista
B1: TIPO | C1: DEPARTAMENTO | D1: INVERSIÓN EN ENTREGA INMEDIATA
B2: Orientacion | C2: (Varios elementos)
B3: Piso | C3: (Varios elementos)
B5: Mín. de Precio VENTA | C5: Etiquetas de columna
B6: PROYECTO | C6: 1D1B | D6: 2D1B | E6: 2D2BM | F6: 2Dg1B | G6: 3D1B | I6: ENTREGA | J6: COMUNA | K6: UPFRONT | L6: PIE | M6: CUOTAS | N6: BONO PIE
B7: Alto Buzeta (MT) | F7: 3128.625 | I7: =VLOOKUP(B7,'Condiciones Comerciales'!B:M,2,FALSE) -> Inmediata | J7: =VLOOKUP(B7,'Condiciones Comerciales'!B:M,3,FALSE) -> Cerrillos | K7: =VLOOKUP(B7,'Condiciones Comerciales'!B:M,7,FALSE) -> 0 | L7: =VLOOKUP(B7,'Condiciones Comerciales'!B:M,8,FALSE) -> 0.1 | M7: =VLOOKUP(B7,'Condiciones Comerciales'!B:M,9,FALSE) -> 60 | N7: =VLOOKUP(B7,'Condiciones Comerciales'!B:M,11,FALSE) -> 0.1
B8: Cáceres | D8: 2700.3375 | F8: 2961.5625 | G8: 3019.275 | I8: =VLOOKUP(B8,'Condiciones Comerciales'!B:M,2,FALSE) -> Inmediata | J8: =VLOOKUP(B8,'Condiciones Comerciales'!B:M,3,FALSE) -> Rancagua | K8: =VLOOKUP(B8,'Condiciones Comerciales'!B:M,7,FALSE) -> 0 | L8: =VLOOKUP(B8,'Condiciones Comerciales'!B:M,8,FALSE) -> 0.1 | M8: =VLOOKUP(B8,'Condiciones Comerciales'!B:M,9,FALSE) -> 60 | N8: =VLOOKUP(B8,'Condiciones Comerciales'!B:M,11,FALSE) -> 0.1
B9: Jardines de Alvarado | C9: 2377.3837 | D9: 2511.4725 | F9: 2666.115 | G9: 2705.265 | I9: =VLOOKUP(B9,'Condiciones Comerciales'!B:M,2,FALSE) -> Inmediata | J9: =VLOOKUP(B9,'Condiciones Comerciales'!B:M,3,FALSE) -> Independencia | K9: =VLOOKUP(B9,'Condiciones Comerciales'!B:M,7,FALSE) -> 0 | L9: =VLOOKUP(B9,'Condiciones Comerciales'!B:M,8,FALSE) -> 0.1 | M9: =VLOOKUP(B9,'Condiciones Comerciales'!B:M,9,FALSE) -> 60 | N9: =VLOOKUP(B9,'Condiciones Comerciales'!B:M,11,FALSE) -> 0.1
B10: Mirador Mapocho | C10: 2479.1737 | E10: 2999.025 | F10: 2922.075 | I10: =VLOOKUP(B10,'Condiciones Comerciales'!B:M,2,FALSE) -> Inmediata | J10: =VLOOKUP(B10,'Condiciones Comerciales'!B:M,3,FALSE) -> Quinta Normal | K10: =VLOOKUP(B10,'Condiciones Comerciales'!B:M,7,FALSE) -> 0 | L10: =VLOOKUP(B10,'Condiciones Comerciales'!B:M,8,FALSE) -> 0.1 | M10: =VLOOKUP(B10,'Condiciones Comerciales'!B:M,9,FALSE) -> 60 | N10: =VLOOKUP(B10,'Condiciones Comerciales'!B:M,11,FALSE) -> 0.1
B11: Pintor Cicarelli I (PC I) | D11: 2806.0762 | E11: 3151.575 | F11: 3044.8912 | G11: 3144.7237 | I11: =VLOOKUP(B11,'Condiciones Comerciales'!B:M,2,FALSE) -> Pre-entrega | J11: =VLOOKUP(B11,'Condiciones Comerciales'!B:M,3,FALSE) -> San Joaquín | K11: =VLOOKUP(B11,'Condiciones Comerciales'!B:M,7,FALSE) -> 0.02 | L11: =VLOOKUP(B11,'Condiciones Comerciales'!B:M,8,FALSE) -> 0.03 | M11: =VLOOKUP(B11,'Condiciones Comerciales'!B:M,9,FALSE) -> 3 | N11: =VLOOKUP(B11,'Condiciones Comerciales'!B:M,11,FALSE) -> 0.15
B12: Pintor Cicarelli II | D12: 2816.8425 | F12: 3038.04 | I12: =VLOOKUP(B12,'Condiciones Comerciales'!B:M,2,FALSE) -> Inmediata | J12: =VLOOKUP(B12,'Condiciones Comerciales'!B:M,3,FALSE) -> San Joaquín | K12: =VLOOKUP(B12,'Condiciones Comerciales'!B:M,7,FALSE) -> 0 | L12: =VLOOKUP(B12,'Condiciones Comerciales'!B:M,8,FALSE) -> 0.1 | M12: =VLOOKUP(B12,'Condiciones Comerciales'!B:M,9,FALSE) -> 60 | N12: =VLOOKUP(B12,'Condiciones Comerciales'!B:M,11,FALSE) -> 0.1
B13: Plaza Cervantes I | D13: 2497.8375 | G13: 2722.6125 | I13: =VLOOKUP(B13,'Condiciones Comerciales'!B:M,2,FALSE) -> Inmediata | J13: =VLOOKUP(B13,'Condiciones Comerciales'!B:M,3,FALSE) -> La Cisterna | K13: =VLOOKUP(B13,'Condiciones Comerciales'!B:M,7,FALSE) -> 0 | L13: =VLOOKUP(B13,'Condiciones Comerciales'!B:M,8,FALSE) -> 0.1 | M13: =VLOOKUP(B13,'Condiciones Comerciales'!B:M,9,FALSE) -> 60 | N13: =VLOOKUP(B13,'Condiciones Comerciales'!B:M,11,FALSE) -> 0.1
B14: Plaza Cervantes II | D14: 2509.9875 | I14: =VLOOKUP(B14,'Condiciones Comerciales'!B:M,2,FALSE) -> Inmediata | J14: =VLOOKUP(B14,'Condiciones Comerciales'!B:M,3,FALSE) -> La Cisterna | K14: =VLOOKUP(B14,'Condiciones Comerciales'!B:M,7,FALSE) -> 0 | L14: =VLOOKUP(B14,'Condiciones Comerciales'!B:M,8,FALSE) -> 0.1 | M14: =VLOOKUP(B14,'Condiciones Comerciales'!B:M,9,FALSE) -> 60 | N14: =VLOOKUP(B14,'Condiciones Comerciales'!B:M,11,FALSE) -> 0.1
B15: Trinidad III | E15: 2627.4375 | I15: =VLOOKUP(B15,'Condiciones Comerciales'!B:M,2,FALSE) -> Inmediata | J15: =VLOOKUP(B15,'Condiciones Comerciales'!B:M,3,FALSE) -> La Cisterna | K15: =VLOOKUP(B15,'Condiciones Comerciales'!B:M,7,FALSE) -> 0 | L15: =VLOOKUP(B15,'Condiciones Comerciales'!B:M,8,FALSE) -> 0.1 | M15: =VLOOKUP(B15,'Condiciones Comerciales'!B:M,9,FALSE) -> 60 | N15: =VLOOKUP(B15,'Condiciones Comerciales'!B:M,11,FALSE) -> 0.1
B16: Vista Costanera | D16: 2344.32 | I16: =VLOOKUP(B16,'Condiciones Comerciales'!B:M,2,FALSE) -> Inmediata | J16: =VLOOKUP(B16,'Condiciones Comerciales'!B:M,3,FALSE) -> Renca | K16: =VLOOKUP(B16,'Condiciones Comerciales'!B:M,7,FALSE) -> 0 | L16: =VLOOKUP(B16,'Condiciones Comerciales'!B:M,8,FALSE) -> 0.1 | M16: =VLOOKUP(B16,'Condiciones Comerciales'!B:M,9,FALSE) -> 60 | N16: =VLOOKUP(B16,'Condiciones Comerciales'!B:M,11,FALSE) -> 0.1
B17: Vista Reloncaví | D17: 2808.675 | F17: 3091.1625 | G17: 3197.7 | I17: =VLOOKUP(B17,'Condiciones Comerciales'!B:M,2,FALSE) -> Inmediata | J17: =VLOOKUP(B17,'Condiciones Comerciales'!B:M,3,FALSE) -> Puerto Montt | K17: =VLOOKUP(B17,'Condiciones Comerciales'!B:M,7,FALSE) -> 0 | L17: =VLOOKUP(B17,'Condiciones Comerciales'!B:M,8,FALSE) -> 0.1 | M17: =VLOOKUP(B17,'Condiciones Comerciales'!B:M,9,FALSE) -> 60 | N17: =VLOOKUP(B17,'Condiciones Comerciales'!B:M,11,FALSE) -> 0.1
B22: TIPO | C22: DEPARTAMENTO | D22: INVERSIÓN EN ENTREGA FUTURA
B23: Orientacion | C23: (Varios elementos)
B24: Piso | C24: (Varios elementos)
B26: Mín. de Precio VENTA | C26: Etiquetas de columna
B27: PROYECTO | C27: 1D1B | D27: 1D1BS | E27: 2D1B | F27: 2D2BM | G27: 2Dg1B | H27: 3D1B | I27: ENTREGA | J27: COMUNA | K27: UPFRONT | L27: PIE | M27: CUOTAS | N27: BONO PIE
B28: General Mackenna | C28: 2296.9125 | E28: 2458.5187 | F28: 2736.7875 | G28: 2644.9875 | H28: 2753.0437 | I28: =VLOOKUP(B28,'Condiciones Comerciales'!B:M,2,FALSE) -> 2029 | J28: =VLOOKUP(B28,'Condiciones Comerciales'!B:M,3,FALSE) -> Temuco | K28: =VLOOKUP(B28,'Condiciones Comerciales'!B:M,7,FALSE) -> 0.01 | L28: =VLOOKUP(B28,'Condiciones Comerciales'!B:M,8,FALSE) -> 0.09 | M28: =VLOOKUP(B28,'Condiciones Comerciales'!B:M,9,FALSE) -> 35 | N28: =VLOOKUP(B28,'Condiciones Comerciales'!B:M,11,FALSE) -> 0.1
B29: SERRANO TORRE A | C29: 2675.025 | E29: 2876.5125 | F29: 3291.6375 | G29: 3173.175 | H29: 3335.175 | I29: =VLOOKUP(B29,'Condiciones Comerciales'!B:M,2,FALSE) -> 2028 | J29: =VLOOKUP(B29,'Condiciones Comerciales'!B:M,3,FALSE) -> Puerto Montt | K29: =VLOOKUP(B29,'Condiciones Comerciales'!B:M,7,FALSE) -> 0.02 | L29: =VLOOKUP(B29,'Condiciones Comerciales'!B:M,8,FALSE) -> 0.08 | M29: =VLOOKUP(B29,'Condiciones Comerciales'!B:M,9,FALSE) -> 21 | N29: =VLOOKUP(B29,'Condiciones Comerciales'!B:M,11,FALSE) -> 0.1
B30: Vista Llacolén A | C30: 2860.3125 | D30: 2580.8625 | F30: 3368.5875 | G30: 3138.75 | I30: =VLOOKUP(B30,'Condiciones Comerciales'!B:M,2,FALSE) -> 2029 | J30: =VLOOKUP(B30,'Condiciones Comerciales'!B:M,3,FALSE) -> Concepción | K30: =VLOOKUP(B30,'Condiciones Comerciales'!B:M,7,FALSE) -> 0.02 | L30: =VLOOKUP(B30,'Condiciones Comerciales'!B:M,8,FALSE) -> 0.08 | M30: =VLOOKUP(B30,'Condiciones Comerciales'!B:M,9,FALSE) -> 34 | N30: =VLOOKUP(B30,'Condiciones Comerciales'!B:M,11,FALSE) -> 0.1
B31: Vista Llacolén B2 | C31: 2633.5125 | F31: 3285.5625 | G31: 3091.1625 | I31: =VLOOKUP(B31,'Condiciones Comerciales'!B:M,2,FALSE) -> 2028 | J31: =VLOOKUP(B31,'Condiciones Comerciales'!B:M,3,FALSE) -> Concepción | K31: =VLOOKUP(B31,'Condiciones Comerciales'!B:M,7,FALSE) -> 0.02 | L31: =VLOOKUP(B31,'Condiciones Comerciales'!B:M,8,FALSE) -> 0.08 | M31: =VLOOKUP(B31,'Condiciones Comerciales'!B:M,9,FALSE) -> 21 | N31: =VLOOKUP(B31,'Condiciones Comerciales'!B:M,11,FALSE) -> 0.1
B32: Vistamar | E32: 2728.6875 | F32: 3260.25 | H32: 3147.8625 | I32: =VLOOKUP(B32,'Condiciones Comerciales'!B:M,2,FALSE) -> 2029 | J32: =VLOOKUP(B32,'Condiciones Comerciales'!B:M,3,FALSE) -> Coquimbo | K32: =VLOOKUP(B32,'Condiciones Comerciales'!B:M,7,FALSE) -> 0.02 | L32: =VLOOKUP(B32,'Condiciones Comerciales'!B:M,8,FALSE) -> 0.08 | M32: =VLOOKUP(B32,'Condiciones Comerciales'!B:M,9,FALSE) -> 34 | N32: =VLOOKUP(B32,'Condiciones Comerciales'!B:M,11,FALSE) -> 0.1

Sheet Reporte_Celdas_Morado
A1: REPORTE: CELDAS EN MORADO — Calculadora BP+Mutuo
A2: Archivo: Stock_Maestra-vigente.xlsx | Hoja: Calculadora BP+Mutuo | Generado automáticamente
A4: RESUMEN EJECUTIVO
A5: Las celdas en morado (#7030A0) en la sección de Financiamiento (filas 35–38) representan el CUADRO DE DISTRIBUCIÓN DEL PRECIO DE VENTA (Tasación).
A6: Son resultados calculados que desglosan cómo se distribuye el precio de venta entre el Certificado de Pago, el Pie pagado y el Crédito Hipotecario.
A7: Estas celdas NO son inputs — son outputs automáticos que dependen de las celdas editables (amarillas y verdes) de la calculadora.
A9: Celda | B9: Etiqueta (Col C) | C9: Fórmula | D9: Resultado actual | E9: Tipo | F9: Descripción / Lógica de cálculo
A10: D35 | B10: Precio de Venta (Tasación) | C10: =D29/D33 | D10: UF 2,887.53 | E10: OUTPUT | F10: Precio de tasación bancaria implícito. Se calcula dividiendo el Crédito Hipotecario (D29) por el porcentaje de financiamiento (D33). Representa el 100% del valor sobre el cual el banco financia.
A11: E35 | B11: (celda auxiliar morada vacía) | C11: (vacía — sin fórmula) | D11: — | E11: AUXILIAR | F11: Celda con formato morado pero sin contenido. Forma parte del bloque visual del cuadro morado (extensión de color de D35). No tiene rol de cálculo.
A12: D36 | B12: Certificado de Pago en UF | C12: =D35-D37-D38 | D12: UF 0 (cuando no hay CP) | E12: OUTPUT | F12: Monto del Certificado de Pago en UF. Se calcula como el residuo: Precio Tasación (D35) menos el Pie Pagado (D37) menos el Crédito Hipotecario (D38). Si no hay certificado de pago (D31=0), esta celda resulta 0.
A13: E36 | B13: % Certificado de Pago | C13: =D36/$D$35 | D13: 0 | E13: OUTPUT % | F13: Porcentaje que representa el Certificado de Pago sobre el Precio de Tasación. D36 ÷ D35 (fijado con $). Complementa E37+E38 para sumar 100%.
A14: D37 | B14: Pie pagado (Reserva+Upfront+Mutuo) | C14: =D25+D27+D28 | D14: UF 144.38 | E14: OUTPUT | F14: Suma total del pie que paga el comprador: Reserva en UF (D25) + Upfront en UF (D27) + Saldo de Pie / Mutuo (D28). Equivale al 5% del precio de venta cuando no hay upfront adicional.
A15: E37 | B15: % Pie pagado | C15: =D37/$D$35 | D15: 0.05 | E15: OUTPUT % | F15: Porcentaje que representa el pie total sobre el Precio de Tasación. D37 ÷ D35. Con pie de 5% y sin certificado, este valor será 5% y E38 será 95%.
A16: D38 | B16: * Crédito Hipotecario | C16: =D35*D33 | D16: UF 2,743.15 | E16: OUTPUT | F16: Monto del crédito hipotecario en UF expresado sobre la tasación. Se calcula como Precio Tasación (D35) × % Financiamiento (D33). Confirma que el banco financia el 95% de la tasación.
A17: E38 | B17: % Crédito Hipotecario | C17: =D38/$D$35 | D17: 0.95 | E17: OUTPUT % | F17: Porcentaje que representa el crédito hipotecario sobre la tasación. D38 ÷ D35. Es el complemento de E37 (pie) + E36 (cert.pago). Los tres porcentajes suman siempre 100%.
A19: MAPA DE DEPENDENCIAS — ¿De dónde vienen los inputs?
A20: Variable | B20: Celda fuente | C20: Color / Tipo | D20: Cómo se llena | E20: Valor actual | F20: Cómo afecta las celdas moradas
A21: % Pie Total (D23) | B21: D23 | C21: VERDE — Input usuario | D21: El usuario escribe directamente el % de pie (ej: 5%). Celda verde editable. | E21: 0.05 | F21: Define el monto de pie (D37) y por ende D35, D36, D38, E36, E37, E38.
A22: % Cert. de Pago (D31) | B22: D31 | C22: VERDE — Input usuario | D22: El usuario ingresa % del Certificado de Pago. Si no hay cert. de pago = 0%. | E22: 0 | F22: Entra en D33 (= 100% - D23 - D31), lo que modifica D35, D38 y E38.
A23: % Financiamiento Banco (D33) | B23: D33 | C23: AMARILLO — Fórmula derivada | D23: =100%-D23-D31. Se calcula automáticamente: es el residuo del pie y cert. de pago. | E23: 0.95 | F23: Es divisor en D35 (=D29/D33) y multiplicador en D38 (=D35*D33). Clave para cálculo del precio de tasación.
A24: Crédito Hipotecario (D29) | B24: D29 | C24: Fórmula interna | D24: =D21*(100%-D23). Precio de venta total × (1 - % pie). Monto que solicita el comprador al banco. | E24: UF 2,743.15 | F24: Es el numerador de D35 (=D29/D33): precio de tasación implícito.
A25: Reserva en UF (D25) | B25: D25 | C25: Fórmula interna | D25: =100000/H23. Convierte $100.000 pesos a UF usando el valor UF del día (H23). | E25: UF 2.51 | F25: Sumando con D27+D28 forma el Pie Pagado total (D37).
A26: Upfront en UF (D27) | B26: D27 | C26: Fórmula interna | D26: =D21*D26 (pago inicial adicional en UF). D26 viene de VLOOKUP a Condiciones Comerciales. | E26: UF 0 | F26: Sumando con D25+D28 forma el Pie Pagado total (D37).
A27: Saldo de Pie/Mutuo (D28) | B27: D28 | C27: Fórmula interna | D27: =IF(D23=0%, 0, D21*D23-D25-D27). Saldo de pie después de reserva y upfront, pagado en cuotas (Mutuo Maestra). | E27: UF 141.87 | F27: Sumando con D25+D27 forma el Pie Pagado total (D37). Principal driver del cuadro morado cuando hay mutuo.
A28: Valor UF del día (H23) | B28: H23 | C28: Input manual — actualizar diariamente | D28: El usuario ingresa el valor de la UF del día en pesos. Usado para convertir $100.000 reserva a UF. | E28: $39.841,72 | F28: Afecta D25 (reserva en UF), que impacta D37, D35, D36, D38 y todos los %.
A30: FLUJO COMPLETO DE CÁLCULO (cadena de dependencias)
A31: PASO 1 → INPUTS USUARIO (celdas amarillas/verdes editables)
A32: D10 (Precio Lista Dpto) | B32: UF 3,319 | C32: Input — celda azul claro. Usuario ingresa precio de lista del departamento.
A33: D15 (% Descuento) | B33: 0.13 | C33: Input — celda amarilla. Usuario define el descuento de venta.
A34: D23 (% Pie) | B34: 0.05 | C34: Input — celda verde. Usuario define el % de pie que aportará el comprador.
A35: D31 (% Cert. Pago) | B35: 0 | C35: Input — celda verde. Usuario define si hay Certificado de Pago y su porcentaje.
A36: H23 (Valor UF) | B36: 39841.72 | C36: Input manual diario. Se actualiza con el valor UF del día para conversión de pesos a UF.
A38: PASO 2 → CÁLCULOS INTERMEDIOS
A39: D18 (Precio Venta Dpto) | B39: =D10*(100%-D15) | C39: UF 2,887.53 → Precio lista menos descuento.
A40: D21 (Total Precio Venta) | B40: =SUM(D18:D20) | C40: UF 2,887.53 → Suma dpto + estac + bodega.
A41: D25 (Reserva en UF) | B41: =100000/H23 | C41: UF 2.51 → $100.000 convertidos al valor UF del día.
A42: D28 (Saldo Pie/Mutuo) | B42: =IF(D23=0%,0,D21*D23-D25-D27) | C42: UF 141.87 → Pie total menos reserva y upfront. Se paga en 60 cuotas.
A43: D29 (Crédito Hipotecario) | B43: =D21*(100%-D23) | C43: UF 2,743.15 → Precio venta × (1 - pie%). Lo que financia el banco.
A44: D33 (% Financiamiento) | B44: =100%-D23-D31 | C44: 95% → Porcentaje que financia el banco (complemento de pie y cert. pago).
A46: PASO 3 → CELDAS MORADAS (outputs finales del cuadro de distribución)
A47: D35 Precio Tasación | B47: =D29/D33 | C47: UF 2,887.53 → Tasación implícita (crédito ÷ % financiamiento)
A48: D37 Pie Total Pagado | B48: =D25+D27+D28 | C48: UF 144.38 → Reserva + Upfront + Mutuo Maestra
A49: D38 Crédito sobre Tasación | B49: =D35*D33 | C49: UF 2,743.15 → 95% de la tasación (confirma el monto que aprobará el banco)
A50: D36 Cert. de Pago en UF | B50: =D35-D37-D38 | C50: UF 0 (cuando no hay Certificado de Pago) → Residuo del cuadro
A51: E36/E37/E38 Porcentajes | B51: =Dx/$D$35 | C51: 0% / 5% / 95% → Cada componente como % del precio de tasación. Suman siempre 100%.

Sheet Reglas_Calculo_Sistema
A1: REGLAS DE CÁLCULO — Calculadora BP + Mutuo
A2: Documento para implementación en sistema. Cada variable indica: qué es, de dónde viene, cómo se calcula y para qué se usa.
A4: SECCIÓN 1: VARIABLES DE ENTRADA (INPUTS)
A5: ID | B5: Variable | C5: Celda Excel | D5: Tipo | E5: Origen / Cómo se llena | F5: Ejemplo actual
A6: IN-01 | B6: proyecto | C6: C7 | D6: Selección usuario | E6: Usuario selecciona el proyecto. Se usa como clave para buscar condiciones comerciales en la hoja 'Condiciones Comerciales' columna B. | F6: Alto Buzeta (MT)
A7: IN-02 | B7: tipo_entrega | C7: D7 | D7: Automático (VLOOKUP) | E7: VLOOKUP(proyecto, 'Condiciones Comerciales'!B3:C21, 2, FALSE). Se busca en columna B y devuelve columna C (Entrega). Determina si es "Inmediata" o año futuro. | F7: Inmediata
A8: IN-03 | B8: precio_lista_depto | C8: D10 | D8: Input usuario (UF) | E8: Precio de lista del departamento en UF. El usuario lo ingresa manualmente o se selecciona de la lista de stock. | F8: UF 3,319
A9: IN-04 | B9: precio_lista_estac | C9: D11 | D9: Input usuario (UF) | E9: Precio de lista del estacionamiento en UF. 0 si no incluye. | F9: UF 0
A10: IN-05 | B10: precio_lista_bodega | C10: D12 | D10: Input usuario (UF) | E10: Precio de lista de la bodega en UF. 0 si no incluye. | F10: UF 0
A11: IN-06 | B11: pct_descuento | C11: D15 | D11: Input usuario (%) | E11: Porcentaje de descuento sobre precio lista. Se aplica SOLO al departamento, NO a estacionamiento ni bodega. | F11: 0.13
A12: IN-07 | B12: pct_pie | C12: D23 | D12: Input usuario (%) | E12: Porcentaje de pie total que debe aportar el comprador. Es la base para calcular el saldo de pie y las cuotas del mutuo. | F12: 0.05
A13: IN-08 | B13: pct_certificado_pago | C13: D31 | D13: Input usuario (%) | E13: Porcentaje del Certificado de Pago (Bono Pie). Si no hay certificado = 0%. Reduce el crédito hipotecario requerido. | F13: 0
A14: IN-09 | B14: pct_upfront | C14: D26 | D14: Automático (VLOOKUP) | E14: VLOOKUP(proyecto, 'Condiciones Comerciales'!B3:M21, 7, FALSE). Devuelve columna H (Upfront). Es el % de pago inicial adicional a la reserva. Ej: 2%, 1% o vacío. | F14: 0% (Alto Buzeta no tiene)
A15: IN-10 | B15: valor_uf | C15: H23 | D15: Input manual ($CLP) | E15: Valor de la UF del día en pesos chilenos. Se usa para convertir la reserva de $100.000 CLP a UF y para mostrar equivalentes en pesos. | F15: 39841.72
A16: IN-11 | B16: reserva_clp | C16: (constante) | D16: Constante fija | E16: Siempre $100.000 CLP. Es la reserva estándar que paga el comprador. Hardcodeada en la fórmula de D25. | F16: 100000
A18: SECCIÓN 2: REGLAS DE CÁLCULO INTERMEDIAS
A19: ID | B19: Variable calculada | C19: Celda | D19: Fórmula Excel | E19: Regla de cálculo (lenguaje sistema) | F19: Nota importante
A20: CALC-01 | B20: precio_venta_depto | C20: D18 | D20: =D10*(100%-D15) | E20: precio_lista_depto × (1 - pct_descuento) | F20: El descuento se aplica SOLO al departamento. Estac. y bodega pasan al precio de venta sin descuento.
A21: CALC-02 | B21: precio_venta_estac | C21: D19 | D21: =D11 | E21: precio_lista_estac (sin descuento) | F21: Pasa directo. No se le aplica descuento.
A22: CALC-03 | B22: precio_venta_bodega | C22: D20 | D22: =D12 | E22: precio_lista_bodega (sin descuento) | F22: Pasa directo. No se le aplica descuento.
A23: CALC-04 | B23: precio_venta_total | C23: D21 | D23: =SUM(D18:D20) | E23: precio_venta_depto + precio_venta_estac + precio_venta_bodega | F23: Variable CLAVE. Es la base para todos los cálculos de pie, crédito y cuotas.
A24: CALC-05 | B24: reserva_uf | C24: D25 | D24: =100000/H23 | E24: reserva_clp ÷ valor_uf = 100000 ÷ valor_uf | F24: Constante $100.000 CLP convertida a UF. Cambia solo si cambia el valor UF del día.
A25: CALC-06 | B25: upfront_uf | C25: D27 | D25: =D21*D26 | E25: precio_venta_total × pct_upfront | F25: Si el proyecto no tiene upfront (columna H vacía en Cond.Comerciales), pct_upfront=0 y este valor=0.
A26: CALC-07 | B26: saldo_pie_mutuo | C26: D28 | D26: =IF(D23=0%,0, D21*D23-D25-D27) | E26: SI pct_pie = 0% → resultado = 0 SINO → (precio_venta_total × pct_pie) - reserva_uf - upfront_uf | F26: Es lo que queda por pagar de pie después de la reserva y el upfront. Se paga en cuotas mensuales (Mutuo Maestra o UF 7).
A27: CALC-08 | B27: credito_hipotecario_venta | C27: D29 | D27: =D21*(100%-D23) | E27: precio_venta_total × (1 - pct_pie) | F27: Monto que el banco financia basado en el precio de VENTA (no tasación). Incluye el certificado de pago si existe.
A28: CALC-09 | B28: pct_financiamiento | C28: D33 | D28: =100%-D23-D31 | E28: 1 - pct_pie - pct_certificado_pago | F28: Porcentaje real que financia el banco sobre la tasación. CLAVE: es el divisor para calcular el precio de tasación implícito.
A30: SECCIÓN 3: CELDAS MORADAS — OUTPUTS FINALES (Cuadro de Distribución de Tasación)
A31: ID | B31: Variable | C31: Celda | D31: Fórmula Excel | E31: Regla de cálculo (lenguaje sistema) | F31: Para qué sirve / Dónde se usa
A32: OUT-01 | B32: precio_tasacion | C32: D35 | D32: =D29/D33 | E32: credito_hipotecario_venta ÷ pct_financiamiento | F32: Es el valor de tasación bancaria implícito. El banco tasa el inmueble a este valor para aprobar el crédito. Es el 100% del cuadro.
A33: OUT-02 | B33: certificado_pago_uf | C33: D36 | D33: =D35-D37-D38 | E33: precio_tasacion - pie_pagado_total - credito_hipotecario_tasacion | F33: Monto del Bono Pie / Certificado de Pago en UF. Es el residuo del cuadro. Si pct_certificado_pago = 0, este valor = 0.
A34: OUT-03 | B34: pie_pagado_total | C34: D37 | D34: =D25+D27+D28 | E34: reserva_uf + upfront_uf + saldo_pie_mutuo | F34: Suma de TODO lo que paga el comprador como pie: reserva $100k + upfront (si hay) + cuotas de mutuo Maestra. Es la porción no financiada por banco.
A35: OUT-04 | B35: credito_hipotecario_tasacion | C35: D38 | D35: =D35*D33 | E35: precio_tasacion × pct_financiamiento | F35: Monto del crédito hipotecario expresado sobre la tasación. Confirma cuánto financia el banco. Se usa para calcular el dividendo mensual.
A36: OUT-05 | B36: pct_certificado_sobre_tasacion | C36: E36 | D36: =D36/$D$35 | E36: certificado_pago_uf ÷ precio_tasacion | F36: % del precio de tasación cubierto por el certificado de pago. Debe coincidir con pct_certificado_pago (IN-08).
A37: OUT-06 | B37: pct_pie_sobre_tasacion | C37: E37 | D37: =D37/$D$35 | E37: pie_pagado_total ÷ precio_tasacion | F37: % del precio de tasación cubierto por el pie del comprador. Debe coincidir con pct_pie (IN-07).
A38: OUT-07 | B38: pct_credito_sobre_tasacion | C38: E38 | D38: =D38/$D$35 | E38: credito_hipotecario_tasacion ÷ precio_tasacion | F38: % del precio de tasación financiado por el banco. Debe coincidir con pct_financiamiento (CALC-09).
A40: SECCIÓN 4: CÁLCULOS ADICIONALES (Cuotas y Dividendos)
A41: ID | B41: Variable | C41: Celda | D41: Fórmula Excel | E41: Regla de cálculo | F41: Nota
A42: CUOTA-01 | B42: cuota_mensual_mutuo | C42: G28 | D42: =IF(tipo_entrega="Inmediata", -PMT(5%/12, 60, saldo_pie_mutuo), 7) | E42: SI tipo_entrega = "Inmediata" → PMT(tasa=5%/12, n=60, VA=saldo_pie_mutuo) SINO → cuota fija de UF 7 | F42: Entrega Inmediata: Mutuo Maestra a 60 meses con 5% anual. Entrega futura: cuotas fijas de UF 7 sin interés.
A43: CUOTA-02 | B43: cuota_mensual_clp | C43: H28 | D43: =G28*H23 | E43: cuota_mensual_mutuo × valor_uf | F43: Equivalente en pesos de la cuota mensual. Solo referencial (el cobro real es en UF).
A44: CUOTA-03 | B44: num_cuotas_enteras (solo UF 7) | C44: G29 | D44: =IF(G28=7, ROUNDDOWN(D28/7,0), "") | E44: Solo si cuota = UF 7 → REDONDEAR.MENOS(saldo_pie_mutuo ÷ 7, 0) | F44: Cuántas cuotas completas de UF 7 caben en el saldo de pie. Solo aplica para entrega futura.
A45: CUOTA-04 | B45: diferencia_cuota (solo UF 7) | C45: G30 | D45: =IF(G28=7, D28-(G28*G29), "") | E45: Solo si cuota = UF 7 → saldo_pie_mutuo - (7 × num_cuotas_enteras) | F45: Diferencia residual que se paga como cuota adicional. Solo entrega futura.
A46: CUOTA-05 | B46: max_cuotas_proyecto (solo UF 7) | C46: G31 | D46: =IF(G28=7, VLOOKUP(proyecto, Cond.Com!B3:J21,9), "") | E46: Solo si cuota = UF 7 → VLOOKUP del máximo de cuotas permitidas por el proyecto (col J, Cond.Comerciales). | F46: Valida que num_cuotas_enteras+1 no exceda el límite del proyecto.
A47: CUOTA-06 | B47: validacion_cuotas | C47: H31 | D47: =IF(G28=7, IF(G31>=(G29+1), "OK","No Cumple"), "") | E47: Solo UF 7 → SI max_cuotas >= (num_cuotas_enteras + 1) → "OK", SINO → "No Cumple" | F47: Si no cumple, se recalculan las cuotas dividiendo saldo_pie entre max_cuotas (G32).
A48: DIV-01 | B48: dividendo_mensual_uf | C48: G38 | D48: =PMT(4%/12, 300, -credito_hip_tasacion) | E48: PMT(tasa=4%/12, n=300, VA= -credito_hipotecario_tasacion) | F48: Dividendo hipotecario mensual a 300 meses (25 años) con tasa 4% anual. USA D38 (celda morada) como capital.
A50: SECCIÓN 5: VALIDACIONES Y REGLAS DE NEGOCIO
A51: # | B51: Regla | E51: Detalle | F51: Acción en sistema
A52: V-01 | B52: Cuadro morado siempre suma 100% | E52: pct_certificado_sobre_tasacion + pct_pie_sobre_tasacion + pct_credito_sobre_tasacion = 100% siempre. Si no suma 100%, hay error de cálculo.
A53: V-02 | B53: Descuento solo aplica a departamento | E53: pct_descuento se multiplica SOLO por precio_lista_depto. Estacionamiento y bodega pasan a precio de venta al 100% de su lista.
A54: V-03 | B54: Bifurcación por tipo de entrega | E54: SI tipo_entrega = "Inmediata" → Mutuo Maestra (60 cuotas, 5% anual, PMT) SINO (entrega futura) → Cuotas fijas de UF 7, con validación de máximo cuotas.
A55: V-04 | B55: Si pie = 0%, saldo_pie = 0 | E55: Cuando pct_pie = 0%, la fórmula de saldo_pie_mutuo (D28) retorna 0 directamente mediante un IF. No hay cuotas que pagar.
A56: V-05 | B56: Constantes del modelo | E56: Reserva = $100,000 CLP (fija) Tasa mutuo Maestra = 5% anual (60 meses) Tasa crédito hipotecario = 4% anual (300 meses = 25 años) Cuota fija entrega futura = UF 7
A57: V-06 | B57: Relación circular D35 ↔ D38 | E57: D35 = D29/D33 y D38 = D35*D33. Matemáticamente: D38 = (D29/D33)*D33 = D29. NO es circular, es una validación cruzada. D38 siempre debe ser igual a D29.
A59: SECCIÓN 6: PSEUDOCÓDIGO COMPLETO (orden de ejecución)
A60: Paso | B60: Código / Lógica
A61: 1 | B61: // INPUTS: recibir del usuario
B62: proyecto, precio_lista_depto, precio_lista_estac, precio_lista_bodega, pct_descuento, pct_pie, pct_certificado_pago, valor_uf
A63: 2 | B63: // LOOKUP: obtener datos del proyecto desde Condiciones Comerciales
B64: tipo_entrega = buscar(proyecto, "Condiciones Comerciales", col_entrega) pct_upfront = buscar(proyecto, "Condiciones Comerciales", col_upfront) max_cuotas_proyecto = buscar(proyecto, "Condiciones Comerciales", col_cuotas)
A65: 3 | B65: // PRECIOS DE VENTA
B66: precio_venta_depto = precio_lista_depto × (1 - pct_descuento) precio_venta_total = precio_venta_depto + precio_lista_estac + precio_lista_bodega
A67: 4 | B67: // COMPONENTES DEL PIE
B68: reserva_uf = 100000 ÷ valor_uf upfront_uf = precio_venta_total × pct_upfront SI pct_pie = 0 ENTONCES saldo_pie_mutuo = 0 SINO saldo_pie_mutuo = (precio_venta_total × pct_pie) - reserva_uf - upfront_uf
A69: 5 | B69: // CRÉDITO Y FINANCIAMIENTO
B70: credito_hipotecario_venta = precio_venta_total × (1 - pct_pie) pct_financiamiento = 1 - pct_pie - pct_certificado_pago
A71: 6 | B71: // ⭐ CELDAS MORADAS: Cuadro de distribución de tasación
B72: precio_tasacion = credito_hipotecario_venta ÷ pct_financiamiento pie_pagado_total = reserva_uf + upfront_uf + saldo_pie_mutuo credito_hipotecario_tasacion = precio_tasacion × pct_financiamiento certificado_pago_uf = precio_tasacion - pie_pagado_total - credito_hipotecario_tasacion pct_cert = certificado_pago_uf ÷ precio_tasacion pct_pie_tas = pie_pagado_total ÷ precio_tasacion pct_cred_tas = credito_hipotecario_tasacion ÷ precio_tasacion
A73: 7 | B73: // CUOTAS DEL PIE
B74: SI tipo_entrega = "Inmediata" ENTONCES cuota_mutuo = PMT(tasa=5%/12, n=60, va=saldo_pie_mutuo) // negativo, tomar valor absoluto SINO cuota_mutuo = UF 7 (fija) num_cuotas = REDONDEAR.MENOS(saldo_pie_mutuo ÷ 7) diferencia = saldo_pie_mutuo - (7 × num_cuotas) SI max_cuotas_proyecto >= num_cuotas + 1 ENTONCES "OK" SINO "No Cumple"
A75: 8 | B75: // DIVIDENDO HIPOTECARIO (usa celda morada D38)
B76: dividendo_mensual = PMT(tasa=4%/12, n=300, va= -credito_hipotecario_tasacion) // 25 años

Sheet Pasos Cálculo
A1: PASOS SECUENCIALES DE CÁLCULO — Calculadora BP+Mutuo
A2: Cálculo de: Precio Venta (Tasación), Certificado de Pago en UF, Pie Pagado y Crédito Hipotecario
A4: Paso | B4: Concepto | C4: Fórmula / Regla de Cálculo | D4: Descripción
B5: DATOS DE ENTRADA (Inputs del usuario)
A6: — | B6: Proyecto | C6: Selección manual del usuario | D6: El usuario elige el proyecto del listado disponible (ej: Alto Buzeta, Vista Llacolén, etc.)
A7: — | B7: Tipo de Entrega | C7: BUSCARV(Proyecto, Condiciones Comerciales, columna 2) | D7: Se obtiene automáticamente desde la tabla Condiciones Comerciales según el proyecto seleccionado (Inmediata o año futuro)
A8: — | B8: Precio de Lista Departamento | C8: Ingreso manual del usuario (en UF) | D8: Precio de lista del departamento seleccionado, ingresado manualmente en UF
A9: — | B9: Precio de Lista Estacionamiento | C9: Ingreso manual del usuario (en UF) | D9: Precio de lista del estacionamiento, ingresado manualmente en UF (puede ser 0)
A10: — | B10: Precio de Lista Bodega | C10: Ingreso manual del usuario (en UF) | D10: Precio de lista de la bodega, ingresado manualmente en UF (puede ser 0)
A11: — | B11: Descuento Venta | C11: Ingreso manual (porcentaje) | D11: Porcentaje de descuento sobre el precio de lista del departamento. Se aplica solo al depto, no a estacionamiento ni bodega
A12: — | B12: Pie Total (%) | C12: Ingreso manual (porcentaje) | D12: Porcentaje del precio total que el comprador pagará como pie (reserva + upfront + saldo pie)
A13: — | B13: Certificado de Pago (%) | C13: Ingreso manual (porcentaje) | D13: Porcentaje del precio total que se cubrirá con Certificado de Pago (Bono Pie). Puede ser 0%
A14: — | B14: Valor UF del día | C14: Ingreso manual o automático (en pesos $) | D14: Valor de la UF en pesos chilenos para convertir montos de UF a pesos
A15: — | B15: % Pago Inicial Upfront | C15: BUSCARV(Proyecto, Condiciones Comerciales, columna 7) | D15: Porcentaje de upfront que se obtiene automáticamente de la tabla Condiciones Comerciales según el proyecto
B17: CÁLCULOS INTERMEDIOS (Pasos secuenciales)
A18: 1 | B18: Precio Venta Departamento | C18: Precio Lista Depto × (1 − Descuento Venta) | D18: Se aplica el descuento solo al departamento. Estacionamiento y bodega se toman a precio de lista sin descuento
A19: 2 | B19: Total Precio Venta | C19: Precio Venta Depto + Estacionamiento + Bodega | D19: Suma de los tres componentes. El estacionamiento y la bodega se toman a su precio de lista original (sin descuento)
A20: 3 | B20: Reserva en UF | C20: $ 100.000 ÷ Valor UF del día | D20: La reserva es siempre $100.000 pesos, convertidos a UF usando el valor de la UF vigente
A21: 4 | B21: Upfront en UF | C21: Total Precio Venta × % Pago Inicial Upfront | D21: Monto de pago inicial (upfront) calculado como porcentaje del precio total. El % viene de Condiciones Comerciales
A22: 5 | B22: Saldo de Pie por pagar | C22: SI(Pie Total = 0%, entonces 0; sino: Total Precio Venta × Pie Total % − Reserva en UF − Upfront en UF) | D22: Es el remanente del pie después de descontar lo ya pagado (reserva y upfront). Si el pie es 0%, el saldo es 0
A23: 6 | B23: Crédito Hipotecario + Certificado Pago (monto combinado) | C23: Total Precio Venta × (1 − Pie Total %) | D23: Es la porción del precio total que NO se paga con pie. Incluye tanto el crédito hipotecario como el certificado de pago
A24: 7 | B24: % Crédito Hipotecario | C24: 1 − Pie Total % − Certificado de Pago % | D24: Porcentaje del precio total que financia el banco. Es el complemento después de restar pie y certificado de pago
B26: RESULTADOS FINALES (Celdas moradas de la Calculadora)
A27: 8 | B27: Precio de Venta (Tasación) | C27: (Crédito Hipotecario + Cert. Pago) ÷ % Crédito Hipotecario | D27: Equivale al Total Precio Venta. Se calcula inverso desde el monto financiado dividido por el % de crédito, para validar consistencia del modelo. Paso 6 ÷ Paso 7
A28: 9 | B28: Pie pagado (Reserva + Upfront + Saldo Pie) | C28: Reserva en UF + Upfront en UF + Saldo de Pie por pagar | D28: Suma de todos los componentes del pie: la reserva ($100.000 convertidos a UF), el pago inicial upfront, y el saldo de pie. Paso 3 + Paso 4 + Paso 5
A29: 10 | B29: Crédito Hipotecario | C29: Precio de Venta (Tasación) × % Crédito Hipotecario | D29: Monto que financia el banco. Es el precio de venta multiplicado por el porcentaje de crédito hipotecario. Paso 8 × Paso 7
A30: 11 | B30: Certificado de Pago en UF | C30: Precio de Venta (Tasación) − Pie pagado − Crédito Hipotecario | D30: Es el residuo: del precio total se resta lo pagado como pie y lo financiado por crédito hipotecario. El remanente es el bono pie (certificado de pago). Paso 8 − Paso 9 − Paso 10
B32: VERIFICACIÓN DE CONSISTENCIA
A33: ✓ | B33: Verificación 1 | C33: Precio Venta (Tasación) = Pie pagado + Crédito Hipotecario + Certificado de Pago en UF | D33: La suma de los 3 componentes (pie + crédito + certificado) debe ser exactamente igual al precio de venta total
A34: ✓ | B34: Verificación 2 | C34: % Pie Total + % Crédito Hipotecario + % Certificado de Pago = 100% | D34: Los tres porcentajes deben sumar exactamente 100% del precio de venta

Sheet Simulador
A1: SIMULADOR DE CÁLCULO — Bono Pie + Crédito Hipotecario
A3: DATOS DE ENTRADA
B4: Concepto | C4: Valor | D4: Unidad | E4: Tipo
A5: 1 | B5: Precio Lista Departamento | C5: 2181 | D5: UF | E5: Manual
A6: 2 | B6: Precio Lista Estacionamiento | C6: 350 | D6: UF | E6: Manual
A7: 3 | B7: Precio Lista Bodega | C7: 80 | D7: UF | E7: Manual
A8: 4 | B8: Descuento Venta | C8: 0.1 | D8: % | E8: ✏️ Manual
A9: 5 | B9: Pie Total | C9: 0.05 | D9: % | E9: ✏️ Manual
A10: 6 | B10: Pago Inicial Upfront | C10: 0.02 | D10: % | E10: ✏️ Manual
A11: 7 | B11: Certificado de Pago | C11: 0.1 | D11: % | E11: ✏️ Manual
A12: 8 | B12: Valor UF del día | C12: 39841.72 | D12: $ | E12: Manual
A14: CÁLCULOS INTERMEDIOS
B15: Concepto | C15: Resultado | D15: Unidad | E15: Fórmula | F15: Depende de | G15: Alimenta a
A16: P1 | B16: Precio Venta Departamento | C16: =C5*(1-C8) -> 1962.9 | D16: UF | E16: Precio Lista Depto × (1 − Descuento Venta) | F16: Precio Lista Depto, Descuento Venta | G16: Total Precio Venta
A17: P2 | B17: Total Precio Venta | C17: =C16+C6+C7 -> 2392.9 | D17: UF | E17: Precio Venta Depto + Estacionamiento + Bodega | F17: P1, Estacionamiento, Bodega | G17: Reserva, Upfront, Saldo Pie, Créd+Cert
A18: P3 | B18: Reserva en UF | C18: =100000/C12 -> 2.5099318 | D18: UF | E18: $100.000 ÷ Valor UF del día | F18: Valor UF | G18: Pie pagado, Saldo Pie
A19: P4 | B19: Upfront en UF | C19: =C17*C10 -> 47.858 | D19: UF | E19: Total Precio Venta × Pago Inicial Upfront % | F19: P2, Pago Inicial Upfront | G19: Pie pagado, Saldo Pie
A20: P5 | B20: Saldo de Pie por pagar | C20: =IF(C9=0,0,C17*C9-C18-C19) -> 69.277068 | D20: UF | E20: SI Pie=0 → 0; sino: Total Precio × Pie% − Reserva − Upfront | F20: P2, Pie Total, P3, P4 | G20: Pie pagado
A21: P6 | B21: Crédito Hip. + Cert. Pago (monto) | C21: =C17*(1-C9) -> 2273.255 | D21: UF | E21: Total Precio Venta × (1 − Pie Total %) | F21: P2, Pie Total | G21: Precio Venta (Tasación)
A22: P7 | B22: % Crédito Hipotecario | C22: =1-C9-C11 -> 0.85 | D22: % | E22: 100% − Pie Total % − Certificado de Pago % | F22: Pie Total, Certificado de Pago | G22: Precio Venta (Tasación), Crédito Hip.
A24: RESULTADOS FINALES
B25: Concepto | C25: Resultado | D25: Unidad | E25: Fórmula | F25: Depende de | G25: Descripción
A26: R1 | B26: Precio de Venta (Tasación) | C26: =C21/C22 -> 2674.4176 | D26: UF | E26: (Créd.Hip.+Cert.Pago) ÷ %Crédito Hip. | F26: P6, P7 | G26: Precio al que tasará el banco. Debe coincidir con Total Precio Venta (P2)
A27: R2 | B27: Pie pagado (Reserva+Upfront+Saldo) | C27: =C18+C19+C20 -> 119.645 | D27: UF | E27: Reserva + Upfront + Saldo Pie | F27: P3, P4, P5 | G27: Todo lo que paga el comprador como pie (efectivo)
A28: R3 | B28: Crédito Hipotecario | C28: =C26*C22 -> 2273.255 | D28: UF | E28: Precio Venta (Tasación) × %Crédito Hip. | F28: R1, P7 | G28: Monto que financia el banco al comprador
A29: R4 | B29: Certificado de Pago en UF | C29: =C26-C27-C28 -> 281.51765 | D29: UF | E29: Tasación − Pie pagado − Crédito Hip. | F29: R1, R2, R3 | G29: Bono pie: lo que cubre el certificado de pago (residuo)
A31: VERIFICACIÓN
B32: Pie + Crédito + Certificado = Tasación | C32: =C27+C28+C29 -> 2674.4176 | D32: UF | E32: =IF(ABS(C32-C26)<0.01,"✅ OK","❌ ERROR") -> ✅ OK
B33: % Pie + % Crédito + % Certificado = 100% | C33: =C9+C22+C11 -> 1 | D33: % | E33: =IF(ABS(C33-1)<0.001,"✅ OK","❌ ERROR") -> ✅ OK
A35: MAPA DE DEPENDENCIAS
B36: Input | C36: Afecta directamente a | E36: Impacto final en resultados
B37: ✏️ Descuento Venta | C37: P1 Precio Venta Depto → P2 Total Precio → P4, P5, P6 | E37: Cambia TODOS los resultados: Tasación, Pie, Crédito y Certificado
B38: ✏️ Pie Total % | C38: P5 Saldo Pie, P6 Créd+Cert, P7 %Crédito | E38: Redistribuye entre Pie, Crédito y Certificado. Tasación no cambia
B39: ✏️ Pago Inicial Upfront % | C39: P4 Upfront → P5 Saldo Pie | E39: Redistribuye DENTRO del pie (Upfront sube, Saldo baja). Totales no cambian
B40: ✏️ Certificado de Pago % | C40: P7 %Crédito Hip. | E40: Redistribuye entre Crédito Hip. y Cert. Pago. Pie y Tasación no cambian
